Workbook

Sheet Assumptions
A1: art-store / shmetsy — Model Assumptions
A2: Edit yellow cells only. Everything else is a formula.
A3: PROFIT IS BEFORE FOUNDER COMPENSATION. Support salaries are modelled; your own pay is not.
A5: Blue = input you can change
A6: Black = formula
A7: Green = pulled from another sheet
A9: CORE DRIVERS | B9: Value | C9: Confidence | D9: Note
A10: GMV per seller / month — LOW | B10: 110 | C10: YOUR DIRECTION | D10: Approximates Etsy platform GMS / active sellers incl. dormant shops. Conservative floor, LOW confidence.
A11: GMV per seller / month — MID | B11: 500 | C11: YOUR DIRECTION | D11: Illustrative: modest but real side-business seller.
A12: GMV per seller / month — HIGH | B12: 2000 | C12: YOUR DIRECTION | D12: Illustrative: seller running this as primary income.
A13: Average order value (AOV) | B13: 50 | C13: UNVERIFIED | D13: Drives orders/mo and the cost of the fixed $0.30 processing fee.
A14: Payment processing — % of GMV | B14: 0.029 | C14: UNVERIFIED | D14: Stripe US card standard. NOT sourced in the research files.
A15: Payment processing — $ per order | B15: 0.3 | C15: UNVERIFIED | D15: Stripe US card standard. NOT sourced in the research files.
A16: Chargeback / refund loss — LOW | B16: 0.005 | C16: UNVERIFIED | D16: No sourced figure exists for art/handmade goods.
A17: Chargeback / refund loss — BASE | B17: 0.01 | C17: UNVERIFIED | D17: Base case used on the Model and Profit Targets tabs.
A18: Chargeback / refund loss — HIGH | B18: 0.02 | C18: UNVERIFIED | D18: Stress case.
A19: Support salary per FTE / year | B19: 80000 | C19: YOUR DIRECTION | D19: Base pay only. W-2 payroll burden (~20%) is NOT included.
A20: Sellers triggering 1st support FTE | B20: 200 | C20: YOUR DIRECTION | D20: Creates the hiring valley — see the Sensitivity tab.
A21: Sellers triggering 2nd support FTE | B21: 2000 | C21: YOUR DIRECTION
A22: Sellers triggering 3rd support FTE | B22: 10000 | C22: YOUR DIRECTION
A23: Retained earnings share of profit | B23: 0.5 | C23: YOUR DIRECTION | D23: Remainder distributed. Losses are absorbed whole, not split.
A24: Customer acquisition cost per seller | B24: 50 | C24: UNVERIFIED | D24: Illustrative placeholder. Only used to translate retained earnings into fundable growth.
A26: FEE TIERS (flat, all-in — platform absorbs processing and loss) | B26: Fee | C26: Net take @ base loss | D26: vs 6%
A27: Tier 1 | B27: 0.06 | C27: =B27-$B$14-($B$15/$B$13)-$B$17 -> 0.015 | D27: =IFERROR(C27/$C$27-1,0) -> 0
A28: Tier 2 | B28: 0.07 | C28: =B28-$B$14-($B$15/$B$13)-$B$17 -> 0.025 | D28: =IFERROR(C28/$C$27-1,0) -> 0.66666667
A29: Tier 3 | B29: 0.08 | C29: =B29-$B$14-($B$15/$B$13)-$B$17 -> 0.035 | D29: =IFERROR(C29/$C$27-1,0) -> 1.3333333
A30: Tier 4 | B30: 0.09 | C30: =B30-$B$14-($B$15/$B$13)-$B$17 -> 0.045 | D30: =IFERROR(C30/$C$27-1,0) -> 2
A32: SELLER SCENARIOS | B32: Sellers | C32: Support FTE | D32: Note
A33: Scenario 1 | B33: 10 | C33: =IF(B33>=$B$22,3,IF(B33>=$B$21,2,IF(B33>=$B$20,1,0))) -> 0 | D33: Support FTE derived from the hire thresholds above.
A34: Scenario 2 | B34: 100 | C34: =IF(B34>=$B$22,3,IF(B34>=$B$21,2,IF(B34>=$B$20,1,0))) -> 0 | D34: Support FTE derived from the hire thresholds above.
A35: Scenario 3 | B35: 1000 | C35: =IF(B35>=$B$22,3,IF(B35>=$B$21,2,IF(B35>=$B$20,1,0))) -> 1 | D35: Support FTE derived from the hire thresholds above.
A36: Scenario 4 | B36: 10000 | C36: =IF(B36>=$B$22,3,IF(B36>=$B$21,2,IF(B36>=$B$20,1,0))) -> 3 | D36: Support FTE derived from the hire thresholds above.
A38: NOT IN THIS MODEL
A39: - Founder compensation. The largest remaining omission — every profit figure is before paying yourself.
A40: - Customer acquisition as a P&L line. CAC appears only as a use of retained earnings, never as a cost of getting there.
A41: - Churn. Seller counts are stock, not flow. Holding 1,843 active sellers may mean acquiring 3,000+.
A42: - Buyer-side demand generation — the thing sellers actually pay a marketplace fee for. The core product risk.
A43: - Stripe Connect payout/transfer fees beyond base processing.
A44: - Marketplace facilitator sales tax and 1099-K issuance.
A45: - Payroll burden on salaries (~20% for W-2): about $48,000/yr at 3 FTE.

Sheet Costs
A1: Operating Cost Stack
A2: Software from tooling-costs-2-users.md and email-crm-costs.md. Labour per your hire thresholds.
A4: SOFTWARE, BY SELLER COUNT (monthly USD)
A5: Line | B5: 10 | C5: 100 | D5: 1,000 | E5: 10,000 | F5: Confidence
A6: Supabase | B6: 25 | C6: 25 | D6: 50 | E6: 225 | F6: HIGH at 10/100 - ESTIMATE at 1k/10k, no basis in the research.
A7: Cloudflare zone | B7: 0 | C7: 0 | D7: 20 | E7: 20 | F7: HIGH. Free covers CDN; Pro $20/mo annual at real traffic.
A8: Cloudflare Workers | B8: 5 | C8: 5 | D8: 25 | E8: 150 | F8: HIGH at 10/100 ($5 min) - ESTIMATE at 1k/10k.
A9: Canva Pro ($15/seat/mo) | B9: 30 | C9: 30 | D9: 60 | E9: 60 | F9: HIGH. Scales with staff seats (2/2/4/4).
A10: GitHub | B10: 0 | C10: 0 | D10: 16 | E10: 16 | F10: HIGH. Free to 2 staff; Team $4/user/mo thereafter.
A11: Domain | B11: 1.56 | C11: 1.56 | D11: 1.56 | E11: 1.56 | F11: HIGH. Fixed regardless of scale.
A12: Customer support | B12: 0 | C12: 0 | D12: 0 | E12: 0 | F12: HIGH. Help Scout Free at every scale - your decision that 1 inbox works.
A13: Email (Kit) | B13: 0 | C13: 0 | D13: 0 | E13: 100 | F13: HIGH to 10k subs - UNVERIFIED above. $100 is a placeholder.
A14: Claude Max 5x ($100/seat) | B14: 200 | C14: 200 | D14: 400 | E14: 400 | F14: HIGH. Team standard seats would cut this ~80% if limits suffice.
A15: Software / month | B15: =SUM(B6:B14) -> 261.56 | C15: =SUM(C6:C14) -> 261.56 | D15: =SUM(D6:D14) -> 572.56 | E15: =SUM(E6:E14) -> 972.56
A16: Software / year | B16: =B15*12 -> 3138.72 | C16: =C15*12 -> 3138.72 | D16: =D15*12 -> 6870.72 | E16: =E15*12 -> 11670.72
A17: Support FTE | B17: =Assumptions!$C$33 -> 0 | C17: =Assumptions!$C$34 -> 0 | D17: =Assumptions!$C$35 -> 1 | E17: =Assumptions!$C$36 -> 3
A18: Support labour / year | B18: =B17*Assumptions!$B$19 -> 0 | C18: =C17*Assumptions!$B$19 -> 0 | D18: =D17*Assumptions!$B$19 -> 80000 | E18: =E17*Assumptions!$B$19 -> 240000
A19: TOTAL OPERATING COST / YEAR | B19: =B16+B18 -> 3138.72 | C19: =C16+C18 -> 3138.72 | D19: =D16+D18 -> 86870.72 | E19: =E16+E18 -> 251670.72
A21: Labour dwarfs software past 200 sellers. At 10,000 sellers software is ~4.6% of operating cost.

Sheet Model
A1: Full Model — annual P&L at the base loss rate
A2: Every cell is a formula off Assumptions and Costs. Change the base loss rate to restress the whole grid.
A3: Support labour IS included. FOUNDER COMPENSATION AND CUSTOMER ACQUISITION ARE NOT.
A5: LOW GMV BAND
A6: GMV band | B6: GMV/seller/mo | C6: Sellers | D6: Annual GMV | E6: Fee | F6: Gross fee rev | G6: Processing | H6: Chargeback loss | I6: Net revenue | J6: Software | K6: Support labour | L6: Profit | M6: Retained | N6: Distributed | O6: Sellers fundable
A7: Low | B7: =Assumptions!$B$10 -> 110 | C7: =Assumptions!$B$33 -> 10 | D7: =B7*C7*12 -> 13200 | E7: =Assumptions!$B$27 -> 0.06 | F7: =D7*E7 -> 792 | G7: =-(D7*Assumptions!$B$14+IFERROR(D7/Assumptions!$B$13,0)*Assumptions!$B$15) -> -462 | H7: =-D7*Assumptions!$B$17 -> -132 | I7: =F7+G7+H7 -> 198 | J7: =-Costs!B$16 -> -3138.72 | K7: =-Costs!B$18 -> 0 | L7: =I7+J7+K7 -> -2940.72 | M7: =IF(L7>0,L7*Assumptions!$B$23,L7) -> -2940.72 | N7: =IF(L7>0,L7*(1-Assumptions!$B$23),0) -> 0 | O7: =IFERROR(MAX(M7,0)/Assumptions!$B$24,0) -> 0
A8: Low | B8: =Assumptions!$B$10 -> 110 | C8: =Assumptions!$B$33 -> 10 | D8: =B8*C8*12 -> 13200 | E8: =Assumptions!$B$28 -> 0.07 | F8: =D8*E8 -> 924 | G8: =-(D8*Assumptions!$B$14+IFERROR(D8/Assumptions!$B$13,0)*Assumptions!$B$15) -> -462 | H8: =-D8*Assumptions!$B$17 -> -132 | I8: =F8+G8+H8 -> 330 | J8: =-Costs!B$16 -> -3138.72 | K8: =-Costs!B$18 -> 0 | L8: =I8+J8+K8 -> -2808.72 | M8: =IF(L8>0,L8*Assumptions!$B$23,L8) -> -2808.72 | N8: =IF(L8>0,L8*(1-Assumptions!$B$23),0) -> 0 | O8: =IFERROR(MAX(M8,0)/Assumptions!$B$24,0) -> 0
A9: Low | B9: =Assumptions!$B$10 -> 110 | C9: =Assumptions!$B$33 -> 10 | D9: =B9*C9*12 -> 13200 | E9: =Assumptions!$B$29 -> 0.08 | F9: =D9*E9 -> 1056 | G9: =-(D9*Assumptions!$B$14+IFERROR(D9/Assumptions!$B$13,0)*Assumptions!$B$15) -> -462 | H9: =-D9*Assumptions!$B$17 -> -132 | I9: =F9+G9+H9 -> 462 | J9: =-Costs!B$16 -> -3138.72 | K9: =-Costs!B$18 -> 0 | L9: =I9+J9+K9 -> -2676.72 | M9: =IF(L9>0,L9*Assumptions!$B$23,L9) -> -2676.72 | N9: =IF(L9>0,L9*(1-Assumptions!$B$23),0) -> 0 | O9: =IFERROR(MAX(M9,0)/Assumptions!$B$24,0) -> 0
A10: Low | B10: =Assumptions!$B$10 -> 110 | C10: =Assumptions!$B$33 -> 10 | D10: =B10*C10*12 -> 13200 | E10: =Assumptions!$B$30 -> 0.09 | F10: =D10*E10 -> 1188 | G10: =-(D10*Assumptions!$B$14+IFERROR(D10/Assumptions!$B$13,0)*Assumptions!$B$15) -> -462 | H10: =-D10*Assumptions!$B$17 -> -132 | I10: =F10+G10+H10 -> 594 | J10: =-Costs!B$16 -> -3138.72 | K10: =-Costs!B$18 -> 0 | L10: =I10+J10+K10 -> -2544.72 | M10: =IF(L10>0,L10*Assumptions!$B$23,L10) -> -2544.72 | N10: =IF(L10>0,L10*(1-Assumptions!$B$23),0) -> 0 | O10: =IFERROR(MAX(M10,0)/Assumptions!$B$24,0) -> 0
A11: Low | B11: =Assumptions!$B$10 -> 110 | C11: =Assumptions!$B$34 -> 100 | D11: =B11*C11*12 -> 132000 | E11: =Assumptions!$B$27 -> 0.06 | F11: =D11*E11 -> 7920 | G11: =-(D11*Assumptions!$B$14+IFERROR(D11/Assumptions!$B$13,0)*Assumptions!$B$15) -> -4620 | H11: =-D11*Assumptions!$B$17 -> -1320 | I11: =F11+G11+H11 -> 1980 | J11: =-Costs!C$16 -> -3138.72 | K11: =-Costs!C$18 -> 0 | L11: =I11+J11+K11 -> -1158.72 | M11: =IF(L11>0,L11*Assumptions!$B$23,L11) -> -1158.72 | N11: =IF(L11>0,L11*(1-Assumptions!$B$23),0) -> 0 | O11: =IFERROR(MAX(M11,0)/Assumptions!$B$24,0) -> 0
A12: Low | B12: =Assumptions!$B$10 -> 110 | C12: =Assumptions!$B$34 -> 100 | D12: =B12*C12*12 -> 132000 | E12: =Assumptions!$B$28 -> 0.07 | F12: =D12*E12 -> 9240 | G12: =-(D12*Assumptions!$B$14+IFERROR(D12/Assumptions!$B$13,0)*Assumptions!$B$15) -> -4620 | H12: =-D12*Assumptions!$B$17 -> -1320 | I12: =F12+G12+H12 -> 3300 | J12: =-Costs!C$16 -> -3138.72 | K12: =-Costs!C$18 -> 0 | L12: =I12+J12+K12 -> 161.28 | M12: =IF(L12>0,L12*Assumptions!$B$23,L12) -> 80.64 | N12: =IF(L12>0,L12*(1-Assumptions!$B$23),0) -> 80.64 | O12: =IFERROR(MAX(M12,0)/Assumptions!$B$24,0) -> 1.6128
A13: Low | B13: =Assumptions!$B$10 -> 110 | C13: =Assumptions!$B$34 -> 100 | D13: =B13*C13*12 -> 132000 | E13: =Assumptions!$B$29 -> 0.08 | F13: =D13*E13 -> 10560 | G13: =-(D13*Assumptions!$B$14+IFERROR(D13/Assumptions!$B$13,0)*Assumptions!$B$15) -> -4620 | H13: =-D13*Assumptions!$B$17 -> -1320 | I13: =F13+G13+H13 -> 4620 | J13: =-Costs!C$16 -> -3138.72 | K13: =-Costs!C$18 -> 0 | L13: =I13+J13+K13 -> 1481.28 | M13: =IF(L13>0,L13*Assumptions!$B$23,L13) -> 740.64 | N13: =IF(L13>0,L13*(1-Assumptions!$B$23),0) -> 740.64 | O13: =IFERROR(MAX(M13,0)/Assumptions!$B$24,0) -> 14.8128
A14: Low | B14: =Assumptions!$B$10 -> 110 | C14: =Assumptions!$B$34 -> 100 | D14: =B14*C14*12 -> 132000 | E14: =Assumptions!$B$30 -> 0.09 | F14: =D14*E14 -> 11880 | G14: =-(D14*Assumptions!$B$14+IFERROR(D14/Assumptions!$B$13,0)*Assumptions!$B$15) -> -4620 | H14: =-D14*Assumptions!$B$17 -> -1320 | I14: =F14+G14+H14 -> 5940 | J14: =-Costs!C$16 -> -3138.72 | K14: =-Costs!C$18 -> 0 | L14: =I14+J14+K14 -> 2801.28 | M14: =IF(L14>0,L14*Assumptions!$B$23,L14) -> 1400.64 | N14: =IF(L14>0,L14*(1-Assumptions!$B$23),0) -> 1400.64 | O14: =IFERROR(MAX(M14,0)/Assumptions!$B$24,0) -> 28.0128
A15: Low | B15: =Assumptions!$B$10 -> 110 | C15: =Assumptions!$B$35 -> 1000 | D15: =B15*C15*12 -> 1320000 | E15: =Assumptions!$B$27 -> 0.06 | F15: =D15*E15 -> 79200 | G15: =-(D15*Assumptions!$B$14+IFERROR(D15/Assumptions!$B$13,0)*Assumptions!$B$15) -> -46200 | H15: =-D15*Assumptions!$B$17 -> -13200 | I15: =F15+G15+H15 -> 19800 | J15: =-Costs!D$16 -> -6870.72 | K15: =-Costs!D$18 -> -80000 | L15: =I15+J15+K15 -> -67070.72 | M15: =IF(L15>0,L15*Assumptions!$B$23,L15) -> -67070.72 | N15: =IF(L15>0,L15*(1-Assumptions!$B$23),0) -> 0 | O15: =IFERROR(MAX(M15,0)/Assumptions!$B$24,0) -> 0
A16: Low | B16: =Assumptions!$B$10 -> 110 | C16: =Assumptions!$B$35 -> 1000 | D16: =B16*C16*12 -> 1320000 | E16: =Assumptions!$B$28 -> 0.07 | F16: =D16*E16 -> 92400 | G16: =-(D16*Assumptions!$B$14+IFERROR(D16/Assumptions!$B$13,0)*Assumptions!$B$15) -> -46200 | H16: =-D16*Assumptions!$B$17 -> -13200 | I16: =F16+G16+H16 -> 33000 | J16: =-Costs!D$16 -> -6870.72 | K16: =-Costs!D$18 -> -80000 | L16: =I16+J16+K16 -> -53870.72 | M16: =IF(L16>0,L16*Assumptions!$B$23,L16) -> -53870.72 | N16: =IF(L16>0,L16*(1-Assumptions!$B$23),0) -> 0 | O16: =IFERROR(MAX(M16,0)/Assumptions!$B$24,0) -> 0
A17: Low | B17: =Assumptions!$B$10 -> 110 | C17: =Assumptions!$B$35 -> 1000 | D17: =B17*C17*12 -> 1320000 | E17: =Assumptions!$B$29 -> 0.08 | F17: =D17*E17 -> 105600 | G17: =-(D17*Assumptions!$B$14+IFERROR(D17/Assumptions!$B$13,0)*Assumptions!$B$15) -> -46200 | H17: =-D17*Assumptions!$B$17 -> -13200 | I17: =F17+G17+H17 -> 46200 | J17: =-Costs!D$16 -> -6870.72 | K17: =-Costs!D$18 -> -80000 | L17: =I17+J17+K17 -> -40670.72 | M17: =IF(L17>0,L17*Assumptions!$B$23,L17) -> -40670.72 | N17: =IF(L17>0,L17*(1-Assumptions!$B$23),0) -> 0 | O17: =IFERROR(MAX(M17,0)/Assumptions!$B$24,0) -> 0
A18: Low | B18: =Assumptions!$B$10 -> 110 | C18: =Assumptions!$B$35 -> 1000 | D18: =B18*C18*12 -> 1320000 | E18: =Assumptions!$B$30 -> 0.09 | F18: =D18*E18 -> 118800 | G18: =-(D18*Assumptions!$B$14+IFERROR(D18/Assumptions!$B$13,0)*Assumptions!$B$15) -> -46200 | H18: =-D18*Assumptions!$B$17 -> -13200 | I18: =F18+G18+H18 -> 59400 | J18: =-Costs!D$16 -> -6870.72 | K18: =-Costs!D$18 -> -80000 | L18: =I18+J18+K18 -> -27470.72 | M18: =IF(L18>0,L18*Assumptions!$B$23,L18) -> -27470.72 | N18: =IF(L18>0,L18*(1-Assumptions!$B$23),0) -> 0 | O18: =IFERROR(MAX(M18,0)/Assumptions!$B$24,0) -> 0
A19: Low | B19: =Assumptions!$B$10 -> 110 | C19: =Assumptions!$B$36 -> 10000 | D19: =B19*C19*12 -> 13200000 | E19: =Assumptions!$B$27 -> 0.06 | F19: =D19*E19 -> 792000 | G19: =-(D19*Assumptions!$B$14+IFERROR(D19/Assumptions!$B$13,0)*Assumptions!$B$15) -> -462000 | H19: =-D19*Assumptions!$B$17 -> -132000 | I19: =F19+G19+H19 -> 198000 | J19: =-Costs!E$16 -> -11670.72 | K19: =-Costs!E$18 -> -240000 | L19: =I19+J19+K19 -> -53670.72 | M19: =IF(L19>0,L19*Assumptions!$B$23,L19) -> -53670.72 | N19: =IF(L19>0,L19*(1-Assumptions!$B$23),0) -> 0 | O19: =IFERROR(MAX(M19,0)/Assumptions!$B$24,0) -> 0
A20: Low | B20: =Assumptions!$B$10 -> 110 | C20: =Assumptions!$B$36 -> 10000 | D20: =B20*C20*12 -> 13200000 | E20: =Assumptions!$B$28 -> 0.07 | F20: =D20*E20 -> 924000 | G20: =-(D20*Assumptions!$B$14+IFERROR(D20/Assumptions!$B$13,0)*Assumptions!$B$15) -> -462000 | H20: =-D20*Assumptions!$B$17 -> -132000 | I20: =F20+G20+H20 -> 330000 | J20: =-Costs!E$16 -> -11670.72 | K20: =-Costs!E$18 -> -240000 | L20: =I20+J20+K20 -> 78329.28 | M20: =IF(L20>0,L20*Assumptions!$B$23,L20) -> 39164.64 | N20: =IF(L20>0,L20*(1-Assumptions!$B$23),0) -> 39164.64 | O20: =IFERROR(MAX(M20,0)/Assumptions!$B$24,0) -> 783.2928
A21: Low | B21: =Assumptions!$B$10 -> 110 | C21: =Assumptions!$B$36 -> 10000 | D21: =B21*C21*12 -> 13200000 | E21: =Assumptions!$B$29 -> 0.08 | F21: =D21*E21 -> 1056000 | G21: =-(D21*Assumptions!$B$14+IFERROR(D21/Assumptions!$B$13,0)*Assumptions!$B$15) -> -462000 | H21: =-D21*Assumptions!$B$17 -> -132000 | I21: =F21+G21+H21 -> 462000 | J21: =-Costs!E$16 -> -11670.72 | K21: =-Costs!E$18 -> -240000 | L21: =I21+J21+K21 -> 210329.28 | M21: =IF(L21>0,L21*Assumptions!$B$23,L21) -> 105164.64 | N21: =IF(L21>0,L21*(1-Assumptions!$B$23),0) -> 105164.64 | O21: =IFERROR(MAX(M21,0)/Assumptions!$B$24,0) -> 2103.2928
A22: Low | B22: =Assumptions!$B$10 -> 110 | C22: =Assumptions!$B$36 -> 10000 | D22: =B22*C22*12 -> 13200000 | E22: =Assumptions!$B$30 -> 0.09 | F22: =D22*E22 -> 1188000 | G22: =-(D22*Assumptions!$B$14+IFERROR(D22/Assumptions!$B$13,0)*Assumptions!$B$15) -> -462000 | H22: =-D22*Assumptions!$B$17 -> -132000 | I22: =F22+G22+H22 -> 594000 | J22: =-Costs!E$16 -> -11670.72 | K22: =-Costs!E$18 -> -240000 | L22: =I22+J22+K22 -> 342329.28 | M22: =IF(L22>0,L22*Assumptions!$B$23,L22) -> 171164.64 | N22: =IF(L22>0,L22*(1-Assumptions!$B$23),0) -> 171164.64 | O22: =IFERROR(MAX(M22,0)/Assumptions!$B$24,0) -> 3423.2928
A25: MID GMV BAND
A26: GMV band | B26: GMV/seller/mo | C26: Sellers | D26: Annual GMV | E26: Fee | F26: Gross fee rev | G26: Processing | H26: Chargeback loss | I26: Net revenue | J26: Software | K26: Support labour | L26: Profit | M26: Retained | N26: Distributed | O26: Sellers fundable
A27: Mid | B27: =Assumptions!$B$11 -> 500 | C27: =Assumptions!$B$33 -> 10 | D27: =B27*C27*12 -> 60000 | E27: =Assumptions!$B$27 -> 0.06 | F27: =D27*E27 -> 3600 | G27: =-(D27*Assumptions!$B$14+IFERROR(D27/Assumptions!$B$13,0)*Assumptions!$B$15) -> -2100 | H27: =-D27*Assumptions!$B$17 -> -600 | I27: =F27+G27+H27 -> 900 | J27: =-Costs!B$16 -> -3138.72 | K27: =-Costs!B$18 -> 0 | L27: =I27+J27+K27 -> -2238.72 | M27: =IF(L27>0,L27*Assumptions!$B$23,L27) -> -2238.72 | N27: =IF(L27>0,L27*(1-Assumptions!$B$23),0) -> 0 | O27: =IFERROR(MAX(M27,0)/Assumptions!$B$24,0) -> 0
A28: Mid | B28: =Assumptions!$B$11 -> 500 | C28: =Assumptions!$B$33 -> 10 | D28: =B28*C28*12 -> 60000 | E28: =Assumptions!$B$28 -> 0.07 | F28: =D28*E28 -> 4200 | G28: =-(D28*Assumptions!$B$14+IFERROR(D28/Assumptions!$B$13,0)*Assumptions!$B$15) -> -2100 | H28: =-D28*Assumptions!$B$17 -> -600 | I28: =F28+G28+H28 -> 1500 | J28: =-Costs!B$16 -> -3138.72 | K28: =-Costs!B$18 -> 0 | L28: =I28+J28+K28 -> -1638.72 | M28: =IF(L28>0,L28*Assumptions!$B$23,L28) -> -1638.72 | N28: =IF(L28>0,L28*(1-Assumptions!$B$23),0) -> 0 | O28: =IFERROR(MAX(M28,0)/Assumptions!$B$24,0) -> 0
A29: Mid | B29: =Assumptions!$B$11 -> 500 | C29: =Assumptions!$B$33 -> 10 | D29: =B29*C29*12 -> 60000 | E29: =Assumptions!$B$29 -> 0.08 | F29: =D29*E29 -> 4800 | G29: =-(D29*Assumptions!$B$14+IFERROR(D29/Assumptions!$B$13,0)*Assumptions!$B$15) -> -2100 | H29: =-D29*Assumptions!$B$17 -> -600 | I29: =F29+G29+H29 -> 2100 | J29: =-Costs!B$16 -> -3138.72 | K29: =-Costs!B$18 -> 0 | L29: =I29+J29+K29 -> -1038.72 | M29: =IF(L29>0,L29*Assumptions!$B$23,L29) -> -1038.72 | N29: =IF(L29>0,L29*(1-Assumptions!$B$23),0) -> 0 | O29: =IFERROR(MAX(M29,0)/Assumptions!$B$24,0) -> 0
A30: Mid | B30: =Assumptions!$B$11 -> 500 | C30: =Assumptions!$B$33 -> 10 | D30: =B30*C30*12 -> 60000 | E30: =Assumptions!$B$30 -> 0.09 | F30: =D30*E30 -> 5400 | G30: =-(D30*Assumptions!$B$14+IFERROR(D30/Assumptions!$B$13,0)*Assumptions!$B$15) -> -2100 | H30: =-D30*Assumptions!$B$17 -> -600 | I30: =F30+G30+H30 -> 2700 | J30: =-Costs!B$16 -> -3138.72 | K30: =-Costs!B$18 -> 0 | L30: =I30+J30+K30 -> -438.72 | M30: =IF(L30>0,L30*Assumptions!$B$23,L30) -> -438.72 | N30: =IF(L30>0,L30*(1-Assumptions!$B$23),0) -> 0 | O30: =IFERROR(MAX(M30,0)/Assumptions!$B$24,0) -> 0
A31: Mid | B31: =Assumptions!$B$11 -> 500 | C31: =Assumptions!$B$34 -> 100 | D31: =B31*C31*12 -> 600000 | E31: =Assumptions!$B$27 -> 0.06 | F31: =D31*E31 -> 36000 | G31: =-(D31*Assumptions!$B$14+IFERROR(D31/Assumptions!$B$13,0)*Assumptions!$B$15) -> -21000 | H31: =-D31*Assumptions!$B$17 -> -6000 | I31: =F31+G31+H31 -> 9000 | J31: =-Costs!C$16 -> -3138.72 | K31: =-Costs!C$18 -> 0 | L31: =I31+J31+K31 -> 5861.28 | M31: =IF(L31>0,L31*Assumptions!$B$23,L31) -> 2930.64 | N31: =IF(L31>0,L31*(1-Assumptions!$B$23),0) -> 2930.64 | O31: =IFERROR(MAX(M31,0)/Assumptions!$B$24,0) -> 58.6128
A32: Mid | B32: =Assumptions!$B$11 -> 500 | C32: =Assumptions!$B$34 -> 100 | D32: =B32*C32*12 -> 600000 | E32: =Assumptions!$B$28 -> 0.07 | F32: =D32*E32 -> 42000 | G32: =-(D32*Assumptions!$B$14+IFERROR(D32/Assumptions!$B$13,0)*Assumptions!$B$15) -> -21000 | H32: =-D32*Assumptions!$B$17 -> -6000 | I32: =F32+G32+H32 -> 15000 | J32: =-Costs!C$16 -> -3138.72 | K32: =-Costs!C$18 -> 0 | L32: =I32+J32+K32 -> 11861.28 | M32: =IF(L32>0,L32*Assumptions!$B$23,L32) -> 5930.64 | N32: =IF(L32>0,L32*(1-Assumptions!$B$23),0) -> 5930.64 | O32: =IFERROR(MAX(M32,0)/Assumptions!$B$24,0) -> 118.6128
A33: Mid | B33: =Assumptions!$B$11 -> 500 | C33: =Assumptions!$B$34 -> 100 | D33: =B33*C33*12 -> 600000 | E33: =Assumptions!$B$29 -> 0.08 | F33: =D33*E33 -> 48000 | G33: =-(D33*Assumptions!$B$14+IFERROR(D33/Assumptions!$B$13,0)*Assumptions!$B$15) -> -21000 | H33: =-D33*Assumptions!$B$17 -> -6000 | I33: =F33+G33+H33 -> 21000 | J33: =-Costs!C$16 -> -3138.72 | K33: =-Costs!C$18 -> 0 | L33: =I33+J33+K33 -> 17861.28 | M33: =IF(L33>0,L33*Assumptions!$B$23,L33) -> 8930.64 | N33: =IF(L33>0,L33*(1-Assumptions!$B$23),0) -> 8930.64 | O33: =IFERROR(MAX(M33,0)/Assumptions!$B$24,0) -> 178.6128
A34: Mid | B34: =Assumptions!$B$11 -> 500 | C34: =Assumptions!$B$34 -> 100 | D34: =B34*C34*12 -> 600000 | E34: =Assumptions!$B$30 -> 0.09 | F34: =D34*E34 -> 54000 | G34: =-(D34*Assumptions!$B$14+IFERROR(D34/Assumptions!$B$13,0)*Assumptions!$B$15) -> -21000 | H34: =-D34*Assumptions!$B$17 -> -6000 | I34: =F34+G34+H34 -> 27000 | J34: =-Costs!C$16 -> -3138.72 | K34: =-Costs!C$18 -> 0 | L34: =I34+J34+K34 -> 23861.28 | M34: =IF(L34>0,L34*Assumptions!$B$23,L34) -> 11930.64 | N34: =IF(L34>0,L34*(1-Assumptions!$B$23),0) -> 11930.64 | O34: =IFERROR(MAX(M34,0)/Assumptions!$B$24,0) -> 238.6128
A35: Mid | B35: =Assumptions!$B$11 -> 500 | C35: =Assumptions!$B$35 -> 1000 | D35: =B35*C35*12 -> 6000000 | E35: =Assumptions!$B$27 -> 0.06 | F35: =D35*E35 -> 360000 | G35: =-(D35*Assumptions!$B$14+IFERROR(D35/Assumptions!$B$13,0)*Assumptions!$B$15) -> -210000 | H35: =-D35*Assumptions!$B$17 -> -60000 | I35: =F35+G35+H35 -> 90000 | J35: =-Costs!D$16 -> -6870.72 | K35: =-Costs!D$18 -> -80000 | L35: =I35+J35+K35 -> 3129.28 | M35: =IF(L35>0,L35*Assumptions!$B$23,L35) -> 1564.64 | N35: =IF(L35>0,L35*(1-Assumptions!$B$23),0) -> 1564.64 | O35: =IFERROR(MAX(M35,0)/Assumptions!$B$24,0) -> 31.2928
A36: Mid | B36: =Assumptions!$B$11 -> 500 | C36: =Assumptions!$B$35 -> 1000 | D36: =B36*C36*12 -> 6000000 | E36: =Assumptions!$B$28 -> 0.07 | F36: =D36*E36 -> 420000 | G36: =-(D36*Assumptions!$B$14+IFERROR(D36/Assumptions!$B$13,0)*Assumptions!$B$15) -> -210000 | H36: =-D36*Assumptions!$B$17 -> -60000 | I36: =F36+G36+H36 -> 150000 | J36: =-Costs!D$16 -> -6870.72 | K36: =-Costs!D$18 -> -80000 | L36: =I36+J36+K36 -> 63129.28 | M36: =IF(L36>0,L36*Assumptions!$B$23,L36) -> 31564.64 | N36: =IF(L36>0,L36*(1-Assumptions!$B$23),0) -> 31564.64 | O36: =IFERROR(MAX(M36,0)/Assumptions!$B$24,0) -> 631.2928
A37: Mid | B37: =Assumptions!$B$11 -> 500 | C37: =Assumptions!$B$35 -> 1000 | D37: =B37*C37*12 -> 6000000 | E37: =Assumptions!$B$29 -> 0.08 | F37: =D37*E37 -> 480000 | G37: =-(D37*Assumptions!$B$14+IFERROR(D37/Assumptions!$B$13,0)*Assumptions!$B$15) -> -210000 | H37: =-D37*Assumptions!$B$17 -> -60000 | I37: =F37+G37+H37 -> 210000 | J37: =-Costs!D$16 -> -6870.72 | K37: =-Costs!D$18 -> -80000 | L37: =I37+J37+K37 -> 123129.28 | M37: =IF(L37>0,L37*Assumptions!$B$23,L37) -> 61564.64 | N37: =IF(L37>0,L37*(1-Assumptions!$B$23),0) -> 61564.64 | O37: =IFERROR(MAX(M37,0)/Assumptions!$B$24,0) -> 1231.2928
A38: Mid | B38: =Assumptions!$B$11 -> 500 | C38: =Assumptions!$B$35 -> 1000 | D38: =B38*C38*12 -> 6000000 | E38: =Assumptions!$B$30 -> 0.09 | F38: =D38*E38 -> 540000 | G38: =-(D38*Assumptions!$B$14+IFERROR(D38/Assumptions!$B$13,0)*Assumptions!$B$15) -> -210000 | H38: =-D38*Assumptions!$B$17 -> -60000 | I38: =F38+G38+H38 -> 270000 | J38: =-Costs!D$16 -> -6870.72 | K38: =-Costs!D$18 -> -80000 | L38: =I38+J38+K38 -> 183129.28 | M38: =IF(L38>0,L38*Assumptions!$B$23,L38) -> 91564.64 | N38: =IF(L38>0,L38*(1-Assumptions!$B$23),0) -> 91564.64 | O38: =IFERROR(MAX(M38,0)/Assumptions!$B$24,0) -> 1831.2928
A39: Mid | B39: =Assumptions!$B$11 -> 500 | C39: =Assumptions!$B$36 -> 10000 | D39: =B39*C39*12 -> 60000000 | E39: =Assumptions!$B$27 -> 0.06 | F39: =D39*E39 -> 3600000 | G39: =-(D39*Assumptions!$B$14+IFERROR(D39/Assumptions!$B$13,0)*Assumptions!$B$15) -> -2100000 | H39: =-D39*Assumptions!$B$17 -> -600000 | I39: =F39+G39+H39 -> 900000 | J39: =-Costs!E$16 -> -11670.72 | K39: =-Costs!E$18 -> -240000 | L39: =I39+J39+K39 -> 648329.28 | M39: =IF(L39>0,L39*Assumptions!$B$23,L39) -> 324164.64 | N39: =IF(L39>0,L39*(1-Assumptions!$B$23),0) -> 324164.64 | O39: =IFERROR(MAX(M39,0)/Assumptions!$B$24,0) -> 6483.2928
A40: Mid | B40: =Assumptions!$B$11 -> 500 | C40: =Assumptions!$B$36 -> 10000 | D40: =B40*C40*12 -> 60000000 | E40: =Assumptions!$B$28 -> 0.07 | F40: =D40*E40 -> 4200000 | G40: =-(D40*Assumptions!$B$14+IFERROR(D40/Assumptions!$B$13,0)*Assumptions!$B$15) -> -2100000 | H40: =-D40*Assumptions!$B$17 -> -600000 | I40: =F40+G40+H40 -> 1500000 | J40: =-Costs!E$16 -> -11670.72 | K40: =-Costs!E$18 -> -240000 | L40: =I40+J40+K40 -> 1248329.3 | M40: =IF(L40>0,L40*Assumptions!$B$23,L40) -> 624164.64 | N40: =IF(L40>0,L40*(1-Assumptions!$B$23),0) -> 624164.64 | O40: =IFERROR(MAX(M40,0)/Assumptions!$B$24,0) -> 12483.293
A41: Mid | B41: =Assumptions!$B$11 -> 500 | C41: =Assumptions!$B$36 -> 10000 | D41: =B41*C41*12 -> 60000000 | E41: =Assumptions!$B$29 -> 0.08 | F41: =D41*E41 -> 4800000 | G41: =-(D41*Assumptions!$B$14+IFERROR(D41/Assumptions!$B$13,0)*Assumptions!$B$15) -> -2100000 | H41: =-D41*Assumptions!$B$17 -> -600000 | I41: =F41+G41+H41 -> 2100000 | J41: =-Costs!E$16 -> -11670.72 | K41: =-Costs!E$18 -> -240000 | L41: =I41+J41+K41 -> 1848329.3 | M41: =IF(L41>0,L41*Assumptions!$B$23,L41) -> 924164.64 | N41: =IF(L41>0,L41*(1-Assumptions!$B$23),0) -> 924164.64 | O41: =IFERROR(MAX(M41,0)/Assumptions!$B$24,0) -> 18483.293
A42: Mid | B42: =Assumptions!$B$11 -> 500 | C42: =Assumptions!$B$36 -> 10000 | D42: =B42*C42*12 -> 60000000 | E42: =Assumptions!$B$30 -> 0.09 | F42: =D42*E42 -> 5400000 | G42: =-(D42*Assumptions!$B$14+IFERROR(D42/Assumptions!$B$13,0)*Assumptions!$B$15) -> -2100000 | H42: =-D42*Assumptions!$B$17 -> -600000 | I42: =F42+G42+H42 -> 2700000 | J42: =-Costs!E$16 -> -11670.72 | K42: =-Costs!E$18 -> -240000 | L42: =I42+J42+K42 -> 2448329.3 | M42: =IF(L42>0,L42*Assumptions!$B$23,L42) -> 1224164.6 | N42: =IF(L42>0,L42*(1-Assumptions!$B$23),0) -> 1224164.6 | O42: =IFERROR(MAX(M42,0)/Assumptions!$B$24,0) -> 24483.293
A45: HIGH GMV BAND
A46: GMV band | B46: GMV/seller/mo | C46: Sellers | D46: Annual GMV | E46: Fee | F46: Gross fee rev | G46: Processing | H46: Chargeback loss | I46: Net revenue | J46: Software | K46: Support labour | L46: Profit | M46: Retained | N46: Distributed | O46: Sellers fundable
A47: High | B47: =Assumptions!$B$12 -> 2000 | C47: =Assumptions!$B$33 -> 10 | D47: =B47*C47*12 -> 240000 | E47: =Assumptions!$B$27 -> 0.06 | F47: =D47*E47 -> 14400 | G47: =-(D47*Assumptions!$B$14+IFERROR(D47/Assumptions!$B$13,0)*Assumptions!$B$15) -> -8400 | H47: =-D47*Assumptions!$B$17 -> -2400 | I47: =F47+G47+H47 -> 3600 | J47: =-Costs!B$16 -> -3138.72 | K47: =-Costs!B$18 -> 0 | L47: =I47+J47+K47 -> 461.28 | M47: =IF(L47>0,L47*Assumptions!$B$23,L47) -> 230.64 | N47: =IF(L47>0,L47*(1-Assumptions!$B$23),0) -> 230.64 | O47: =IFERROR(MAX(M47,0)/Assumptions!$B$24,0) -> 4.6128
A48: High | B48: =Assumptions!$B$12 -> 2000 | C48: =Assumptions!$B$33 -> 10 | D48: =B48*C48*12 -> 240000 | E48: =Assumptions!$B$28 -> 0.07 | F48: =D48*E48 -> 16800 | G48: =-(D48*Assumptions!$B$14+IFERROR(D48/Assumptions!$B$13,0)*Assumptions!$B$15) -> -8400 | H48: =-D48*Assumptions!$B$17 -> -2400 | I48: =F48+G48+H48 -> 6000 | J48: =-Costs!B$16 -> -3138.72 | K48: =-Costs!B$18 -> 0 | L48: =I48+J48+K48 -> 2861.28 | M48: =IF(L48>0,L48*Assumptions!$B$23,L48) -> 1430.64 | N48: =IF(L48>0,L48*(1-Assumptions!$B$23),0) -> 1430.64 | O48: =IFERROR(MAX(M48,0)/Assumptions!$B$24,0) -> 28.6128
A49: High | B49: =Assumptions!$B$12 -> 2000 | C49: =Assumptions!$B$33 -> 10 | D49: =B49*C49*12 -> 240000 | E49: =Assumptions!$B$29 -> 0.08 | F49: =D49*E49 -> 19200 | G49: =-(D49*Assumptions!$B$14+IFERROR(D49/Assumptions!$B$13,0)*Assumptions!$B$15) -> -8400 | H49: =-D49*Assumptions!$B$17 -> -2400 | I49: =F49+G49+H49 -> 8400 | J49: =-Costs!B$16 -> -3138.72 | K49: =-Costs!B$18 -> 0 | L49: =I49+J49+K49 -> 5261.28 | M49: =IF(L49>0,L49*Assumptions!$B$23,L49) -> 2630.64 | N49: =IF(L49>0,L49*(1-Assumptions!$B$23),0) -> 2630.64 | O49: =IFERROR(MAX(M49,0)/Assumptions!$B$24,0) -> 52.6128
A50: High | B50: =Assumptions!$B$12 -> 2000 | C50: =Assumptions!$B$33 -> 10 | D50: =B50*C50*12 -> 240000 | E50: =Assumptions!$B$30 -> 0.09 | F50: =D50*E50 -> 21600 | G50: =-(D50*Assumptions!$B$14+IFERROR(D50/Assumptions!$B$13,0)*Assumptions!$B$15) -> -8400 | H50: =-D50*Assumptions!$B$17 -> -2400 | I50: =F50+G50+H50 -> 10800 | J50: =-Costs!B$16 -> -3138.72 | K50: =-Costs!B$18 -> 0 | L50: =I50+J50+K50 -> 7661.28 | M50: =IF(L50>0,L50*Assumptions!$B$23,L50) -> 3830.64 | N50: =IF(L50>0,L50*(1-Assumptions!$B$23),0) -> 3830.64 | O50: =IFERROR(MAX(M50,0)/Assumptions!$B$24,0) -> 76.6128
A51: High | B51: =Assumptions!$B$12 -> 2000 | C51: =Assumptions!$B$34 -> 100 | D51: =B51*C51*12 -> 2400000 | E51: =Assumptions!$B$27 -> 0.06 | F51: =D51*E51 -> 144000 | G51: =-(D51*Assumptions!$B$14+IFERROR(D51/Assumptions!$B$13,0)*Assumptions!$B$15) -> -84000 | H51: =-D51*Assumptions!$B$17 -> -24000 | I51: =F51+G51+H51 -> 36000 | J51: =-Costs!C$16 -> -3138.72 | K51: =-Costs!C$18 -> 0 | L51: =I51+J51+K51 -> 32861.28 | M51: =IF(L51>0,L51*Assumptions!$B$23,L51) -> 16430.64 | N51: =IF(L51>0,L51*(1-Assumptions!$B$23),0) -> 16430.64 | O51: =IFERROR(MAX(M51,0)/Assumptions!$B$24,0) -> 328.6128
A52: High | B52: =Assumptions!$B$12 -> 2000 | C52: =Assumptions!$B$34 -> 100 | D52: =B52*C52*12 -> 2400000 | E52: =Assumptions!$B$28 -> 0.07 | F52: =D52*E52 -> 168000 | G52: =-(D52*Assumptions!$B$14+IFERROR(D52/Assumptions!$B$13,0)*Assumptions!$B$15) -> -84000 | H52: =-D52*Assumptions!$B$17 -> -24000 | I52: =F52+G52+H52 -> 60000 | J52: =-Costs!C$16 -> -3138.72 | K52: =-Costs!C$18 -> 0 | L52: =I52+J52+K52 -> 56861.28 | M52: =IF(L52>0,L52*Assumptions!$B$23,L52) -> 28430.64 | N52: =IF(L52>0,L52*(1-Assumptions!$B$23),0) -> 28430.64 | O52: =IFERROR(MAX(M52,0)/Assumptions!$B$24,0) -> 568.6128
A53: High | B53: =Assumptions!$B$12 -> 2000 | C53: =Assumptions!$B$34 -> 100 | D53: =B53*C53*12 -> 2400000 | E53: =Assumptions!$B$29 -> 0.08 | F53: =D53*E53 -> 192000 | G53: =-(D53*Assumptions!$B$14+IFERROR(D53/Assumptions!$B$13,0)*Assumptions!$B$15) -> -84000 | H53: =-D53*Assumptions!$B$17 -> -24000 | I53: =F53+G53+H53 -> 84000 | J53: =-Costs!C$16 -> -3138.72 | K53: =-Costs!C$18 -> 0 | L53: =I53+J53+K53 -> 80861.28 | M53: =IF(L53>0,L53*Assumptions!$B$23,L53) -> 40430.64 | N53: =IF(L53>0,L53*(1-Assumptions!$B$23),0) -> 40430.64 | O53: =IFERROR(MAX(M53,0)/Assumptions!$B$24,0) -> 808.6128
A54: High | B54: =Assumptions!$B$12 -> 2000 | C54: =Assumptions!$B$34 -> 100 | D54: =B54*C54*12 -> 2400000 | E54: =Assumptions!$B$30 -> 0.09 | F54: =D54*E54 -> 216000 | G54: =-(D54*Assumptions!$B$14+IFERROR(D54/Assumptions!$B$13,0)*Assumptions!$B$15) -> -84000 | H54: =-D54*Assumptions!$B$17 -> -24000 | I54: =F54+G54+H54 -> 108000 | J54: =-Costs!C$16 -> -3138.72 | K54: =-Costs!C$18 -> 0 | L54: =I54+J54+K54 -> 104861.28 | M54: =IF(L54>0,L54*Assumptions!$B$23,L54) -> 52430.64 | N54: =IF(L54>0,L54*(1-Assumptions!$B$23),0) -> 52430.64 | O54: =IFERROR(MAX(M54,0)/Assumptions!$B$24,0) -> 1048.6128
A55: High | B55: =Assumptions!$B$12 -> 2000 | C55: =Assumptions!$B$35 -> 1000 | D55: =B55*C55*12 -> 24000000 | E55: =Assumptions!$B$27 -> 0.06 | F55: =D55*E55 -> 1440000 | G55: =-(D55*Assumptions!$B$14+IFERROR(D55/Assumptions!$B$13,0)*Assumptions!$B$15) -> -840000 | H55: =-D55*Assumptions!$B$17 -> -240000 | I55: =F55+G55+H55 -> 360000 | J55: =-Costs!D$16 -> -6870.72 | K55: =-Costs!D$18 -> -80000 | L55: =I55+J55+K55 -> 273129.28 | M55: =IF(L55>0,L55*Assumptions!$B$23,L55) -> 136564.64 | N55: =IF(L55>0,L55*(1-Assumptions!$B$23),0) -> 136564.64 | O55: =IFERROR(MAX(M55,0)/Assumptions!$B$24,0) -> 2731.2928
A56: High | B56: =Assumptions!$B$12 -> 2000 | C56: =Assumptions!$B$35 -> 1000 | D56: =B56*C56*12 -> 24000000 | E56: =Assumptions!$B$28 -> 0.07 | F56: =D56*E56 -> 1680000 | G56: =-(D56*Assumptions!$B$14+IFERROR(D56/Assumptions!$B$13,0)*Assumptions!$B$15) -> -840000 | H56: =-D56*Assumptions!$B$17 -> -240000 | I56: =F56+G56+H56 -> 600000 | J56: =-Costs!D$16 -> -6870.72 | K56: =-Costs!D$18 -> -80000 | L56: =I56+J56+K56 -> 513129.28 | M56: =IF(L56>0,L56*Assumptions!$B$23,L56) -> 256564.64 | N56: =IF(L56>0,L56*(1-Assumptions!$B$23),0) -> 256564.64 | O56: =IFERROR(MAX(M56,0)/Assumptions!$B$24,0) -> 5131.2928
A57: High | B57: =Assumptions!$B$12 -> 2000 | C57: =Assumptions!$B$35 -> 1000 | D57: =B57*C57*12 -> 24000000 | E57: =Assumptions!$B$29 -> 0.08 | F57: =D57*E57 -> 1920000 | G57: =-(D57*Assumptions!$B$14+IFERROR(D57/Assumptions!$B$13,0)*Assumptions!$B$15) -> -840000 | H57: =-D57*Assumptions!$B$17 -> -240000 | I57: =F57+G57+H57 -> 840000 | J57: =-Costs!D$16 -> -6870.72 | K57: =-Costs!D$18 -> -80000 | L57: =I57+J57+K57 -> 753129.28 | M57: =IF(L57>0,L57*Assumptions!$B$23,L57) -> 376564.64 | N57: =IF(L57>0,L57*(1-Assumptions!$B$23),0) -> 376564.64 | O57: =IFERROR(MAX(M57,0)/Assumptions!$B$24,0) -> 7531.2928
A58: High | B58: =Assumptions!$B$12 -> 2000 | C58: =Assumptions!$B$35 -> 1000 | D58: =B58*C58*12 -> 24000000 | E58: =Assumptions!$B$30 -> 0.09 | F58: =D58*E58 -> 2160000 | G58: =-(D58*Assumptions!$B$14+IFERROR(D58/Assumptions!$B$13,0)*Assumptions!$B$15) -> -840000 | H58: =-D58*Assumptions!$B$17 -> -240000 | I58: =F58+G58+H58 -> 1080000 | J58: =-Costs!D$16 -> -6870.72 | K58: =-Costs!D$18 -> -80000 | L58: =I58+J58+K58 -> 993129.28 | M58: =IF(L58>0,L58*Assumptions!$B$23,L58) -> 496564.64 | N58: =IF(L58>0,L58*(1-Assumptions!$B$23),0) -> 496564.64 | O58: =IFERROR(MAX(M58,0)/Assumptions!$B$24,0) -> 9931.2928
A59: High | B59: =Assumptions!$B$12 -> 2000 | C59: =Assumptions!$B$36 -> 10000 | D59: =B59*C59*12 -> 240000000 | E59: =Assumptions!$B$27 -> 0.06 | F59: =D59*E59 -> 14400000 | G59: =-(D59*Assumptions!$B$14+IFERROR(D59/Assumptions!$B$13,0)*Assumptions!$B$15) -> -8400000 | H59: =-D59*Assumptions!$B$17 -> -2400000 | I59: =F59+G59+H59 -> 3600000 | J59: =-Costs!E$16 -> -11670.72 | K59: =-Costs!E$18 -> -240000 | L59: =I59+J59+K59 -> 3348329.3 | M59: =IF(L59>0,L59*Assumptions!$B$23,L59) -> 1674164.6 | N59: =IF(L59>0,L59*(1-Assumptions!$B$23),0) -> 1674164.6 | O59: =IFERROR(MAX(M59,0)/Assumptions!$B$24,0) -> 33483.293
A60: High | B60: =Assumptions!$B$12 -> 2000 | C60: =Assumptions!$B$36 -> 10000 | D60: =B60*C60*12 -> 240000000 | E60: =Assumptions!$B$28 -> 0.07 | F60: =D60*E60 -> 16800000 | G60: =-(D60*Assumptions!$B$14+IFERROR(D60/Assumptions!$B$13,0)*Assumptions!$B$15) -> -8400000 | H60: =-D60*Assumptions!$B$17 -> -2400000 | I60: =F60+G60+H60 -> 6000000 | J60: =-Costs!E$16 -> -11670.72 | K60: =-Costs!E$18 -> -240000 | L60: =I60+J60+K60 -> 5748329.3 | M60: =IF(L60>0,L60*Assumptions!$B$23,L60) -> 2874164.6 | N60: =IF(L60>0,L60*(1-Assumptions!$B$23),0) -> 2874164.6 | O60: =IFERROR(MAX(M60,0)/Assumptions!$B$24,0) -> 57483.293
A61: High | B61: =Assumptions!$B$12 -> 2000 | C61: =Assumptions!$B$36 -> 10000 | D61: =B61*C61*12 -> 240000000 | E61: =Assumptions!$B$29 -> 0.08 | F61: =D61*E61 -> 19200000 | G61: =-(D61*Assumptions!$B$14+IFERROR(D61/Assumptions!$B$13,0)*Assumptions!$B$15) -> -8400000 | H61: =-D61*Assumptions!$B$17 -> -2400000 | I61: =F61+G61+H61 -> 8400000 | J61: =-Costs!E$16 -> -11670.72 | K61: =-Costs!E$18 -> -240000 | L61: =I61+J61+K61 -> 8148329.3 | M61: =IF(L61>0,L61*Assumptions!$B$23,L61) -> 4074164.6 | N61: =IF(L61>0,L61*(1-Assumptions!$B$23),0) -> 4074164.6 | O61: =IFERROR(MAX(M61,0)/Assumptions!$B$24,0) -> 81483.293
A62: High | B62: =Assumptions!$B$12 -> 2000 | C62: =Assumptions!$B$36 -> 10000 | D62: =B62*C62*12 -> 240000000 | E62: =Assumptions!$B$30 -> 0.09 | F62: =D62*E62 -> 21600000 | G62: =-(D62*Assumptions!$B$14+IFERROR(D62/Assumptions!$B$13,0)*Assumptions!$B$15) -> -8400000 | H62: =-D62*Assumptions!$B$17 -> -2400000 | I62: =F62+G62+H62 -> 10800000 | J62: =-Costs!E$16 -> -11670.72 | K62: =-Costs!E$18 -> -240000 | L62: =I62+J62+K62 -> 10548329 | M62: =IF(L62>0,L62*Assumptions!$B$23,L62) -> 5274164.6 | N62: =IF(L62>0,L62*(1-Assumptions!$B$23),0) -> 5274164.6 | O62: =IFERROR(MAX(M62,0)/Assumptions!$B$24,0) -> 105483.29

Sheet Sensitivity
A1: Sensitivity — where the model breaks
A3: 1. NET TAKE RATE by fee and loss rate
A4: Fee | B4: =Assumptions!$B$16 -> 0.005 | C4: =Assumptions!$B$17 -> 0.01 | D4: =Assumptions!$B$18 -> 0.02
A5: =Assumptions!$B$27 -> 0.06 | B5: =$A5-Assumptions!$B$14-(Assumptions!$B$15/Assumptions!$B$13)-Assumptions!$B$16 -> 0.02 | C5: =$A5-Assumptions!$B$14-(Assumptions!$B$15/Assumptions!$B$13)-Assumptions!$B$17 -> 0.015 | D5: =$A5-Assumptions!$B$14-(Assumptions!$B$15/Assumptions!$B$13)-Assumptions!$B$18 -> 0.005
A6: =Assumptions!$B$28 -> 0.07 | B6: =$A6-Assumptions!$B$14-(Assumptions!$B$15/Assumptions!$B$13)-Assumptions!$B$16 -> 0.03 | C6: =$A6-Assumptions!$B$14-(Assumptions!$B$15/Assumptions!$B$13)-Assumptions!$B$17 -> 0.025 | D6: =$A6-Assumptions!$B$14-(Assumptions!$B$15/Assumptions!$B$13)-Assumptions!$B$18 -> 0.015
A7: =Assumptions!$B$29 -> 0.08 | B7: =$A7-Assumptions!$B$14-(Assumptions!$B$15/Assumptions!$B$13)-Assumptions!$B$16 -> 0.04 | C7: =$A7-Assumptions!$B$14-(Assumptions!$B$15/Assumptions!$B$13)-Assumptions!$B$17 -> 0.035 | D7: =$A7-Assumptions!$B$14-(Assumptions!$B$15/Assumptions!$B$13)-Assumptions!$B$18 -> 0.025
A8: =Assumptions!$B$30 -> 0.09 | B8: =$A8-Assumptions!$B$14-(Assumptions!$B$15/Assumptions!$B$13)-Assumptions!$B$16 -> 0.05 | C8: =$A8-Assumptions!$B$14-(Assumptions!$B$15/Assumptions!$B$13)-Assumptions!$B$17 -> 0.045 | D8: =$A8-Assumptions!$B$14-(Assumptions!$B$15/Assumptions!$B$13)-Assumptions!$B$18 -> 0.035
A10: A 6% fee at a 2% loss rate nets 0.5%. That combination does not survive at any seller count.
A12: 2. AOV SENSITIVITY (at base loss rate)
A13: AOV | B13: =Assumptions!$B$27 -> 0.06 | C13: =Assumptions!$B$28 -> 0.07 | D13: =Assumptions!$B$29 -> 0.08 | E13: =Assumptions!$B$30 -> 0.09
A14: 10 | B14: =Assumptions!$B$27-Assumptions!$B$14-(Assumptions!$B$15/$A14)-Assumptions!$B$17 -> -0.009 | C14: =Assumptions!$B$28-Assumptions!$B$14-(Assumptions!$B$15/$A14)-Assumptions!$B$17 -> 0.001 | D14: =Assumptions!$B$29-Assumptions!$B$14-(Assumptions!$B$15/$A14)-Assumptions!$B$17 -> 0.011 | E14: =Assumptions!$B$30-Assumptions!$B$14-(Assumptions!$B$15/$A14)-Assumptions!$B$17 -> 0.021
A15: 25 | B15: =Assumptions!$B$27-Assumptions!$B$14-(Assumptions!$B$15/$A15)-Assumptions!$B$17 -> 0.009 | C15: =Assumptions!$B$28-Assumptions!$B$14-(Assumptions!$B$15/$A15)-Assumptions!$B$17 -> 0.019 | D15: =Assumptions!$B$29-Assumptions!$B$14-(Assumptions!$B$15/$A15)-Assumptions!$B$17 -> 0.029 | E15: =Assumptions!$B$30-Assumptions!$B$14-(Assumptions!$B$15/$A15)-Assumptions!$B$17 -> 0.039
A16: 50 | B16: =Assumptions!$B$27-Assumptions!$B$14-(Assumptions!$B$15/$A16)-Assumptions!$B$17 -> 0.015 | C16: =Assumptions!$B$28-Assumptions!$B$14-(Assumptions!$B$15/$A16)-Assumptions!$B$17 -> 0.025 | D16: =Assumptions!$B$29-Assumptions!$B$14-(Assumptions!$B$15/$A16)-Assumptions!$B$17 -> 0.035 | E16: =Assumptions!$B$30-Assumptions!$B$14-(Assumptions!$B$15/$A16)-Assumptions!$B$17 -> 0.045
A17: 100 | B17: =Assumptions!$B$27-Assumptions!$B$14-(Assumptions!$B$15/$A17)-Assumptions!$B$17 -> 0.018 | C17: =Assumptions!$B$28-Assumptions!$B$14-(Assumptions!$B$15/$A17)-Assumptions!$B$17 -> 0.028 | D17: =Assumptions!$B$29-Assumptions!$B$14-(Assumptions!$B$15/$A17)-Assumptions!$B$17 -> 0.038 | E17: =Assumptions!$B$30-Assumptions!$B$14-(Assumptions!$B$15/$A17)-Assumptions!$B$17 -> 0.048
A18: 250 | B18: =Assumptions!$B$27-Assumptions!$B$14-(Assumptions!$B$15/$A18)-Assumptions!$B$17 -> 0.0198 | C18: =Assumptions!$B$28-Assumptions!$B$14-(Assumptions!$B$15/$A18)-Assumptions!$B$17 -> 0.0298 | D18: =Assumptions!$B$29-Assumptions!$B$14-(Assumptions!$B$15/$A18)-Assumptions!$B$17 -> 0.0398 | E18: =Assumptions!$B$30-Assumptions!$B$14-(Assumptions!$B$15/$A18)-Assumptions!$B$17 -> 0.0498
A21: 3. THE HIRING VALLEY — first hire lands at 200 sellers, before the revenue does
A22: At 8%, base loss. 'Recover at' is where profit returns to zero after the salary lands.
A23: GMV band | B23: Breakeven before hire | C23: Hire at | D23: Recover at | E23: Growth needed to recover
A24: Low ($110/mo) | B24: 68 | C24: 200 | D24: 1800 | E24: 9.0x
A25: Mid ($500/mo) | B25: 15 | C25: 200 | D25: 396 | E25: 2.0x
A26: High ($2,000/mo) | B26: 4 | C26: - | D26: - | E26: no valley
A28: In the low band the valley runs 200 -> 1,800 sellers: 9x growth to climb back to breakeven. The difference between hiring at 200 and hiring at 600 is roughly a year of runway.
A31: 4. COMPETITIVE REFERENCE — what a seller pays on a $50 order
A32: Platform / scenario | B32: Seller pays | C32: Source
A33: art-store @ 6% | B33: 0.06 | C33: By construction
A34: art-store @ 7% | B34: 0.07 | C34: By construction
A35: art-store @ 8% | B35: 0.08 | C35: By construction
A36: art-store @ 9% | B36: 0.09 | C36: By construction
A37: Etsy baseline, US seller, no ads | B37: 0.104 | C37: etsy-fees-and-pricing-model.md s5.1 - HIGH
A38: Etsy + Offsite Ads, 12% tier | B38: 0.224 | C38: etsy-fees-and-pricing-model.md s5.2 - HIGH
A39: Etsy + Offsite Ads, 15% tier | B39: 0.254 | C39: etsy-fees-and-pricing-model.md s5.2 - HIGH

Sheet Profit Targets
A1: What Would Have To Be True — Profit Targets
A2: Solves the model backwards. Change the targets in yellow; everything recalculates.
A3: PROFIT BEFORE FOUNDER COMPENSATION. Two founders at $120,000 turns a $300,000 target into $540,000.
A5: COST STEPS APPLIED | B5: Seller range | C5: Software /yr | D5: FTE | E5: Labour /yr | F5: Total fixed /yr
A6: Step 1 | B6: 0 - 199 | C6: 3138.72 | D6: 0 | E6: =D6*Assumptions!$B$19 -> 0 | F6: =C6+E6 -> 3138.72
A7: Step 2 | B7: 200 - 999 | C7: 3138.72 | D7: 1 | E7: =D7*Assumptions!$B$19 -> 80000 | F7: =C7+E7 -> 83138.72
A8: Step 3 | B8: 1,000 - 1,999 | C8: 6870.72 | D8: 1 | E8: =D8*Assumptions!$B$19 -> 80000 | F8: =C8+E8 -> 86870.72
A9: Step 4 | B9: 2,000 - 9,999 | C9: 6870.72 | D9: 2 | E9: =D9*Assumptions!$B$19 -> 160000 | F9: =C9+E9 -> 166870.72
A10: Step 5 | B10: 10,000 and above | C10: 11670.72 | D10: 3 | E10: =D10*Assumptions!$B$19 -> 240000 | F10: =C10+E10 -> 251670.72
A12: PROFIT TARGETS
A13: Target 1 | B13: 100000
A14: Target 2 | B14: 300000
A15: Target 3 | B15: 500000
A17: TABLE A - SELLERS REQUIRED (base loss rate)
A18: Profit target | B18: Fee | C18: Low band | D18: Mid band | E18: High band
A19: =$B$13 -> 100000 | B19: =Assumptions!$B$27 -> 0.06 | C19: =IFERROR(IF((($A19+$F$6)/(Assumptions!$B$10*12*Assumptions!$C$27))<200,ROUNDUP((($A19+$F$6)/(Assumptions!$B$10*12*Assumptions!$C$27)),0),IF((($A19+$F$7)/(Assumptions!$B$10*12*Assumptions!$C$27))<1000,ROUNDUP((($A19+$F$7)/(Assumptions!$B$10*12*Assumptions!$C$27)),0),IF((($A19+$F$8)/(Assumptions!$B$10*12*Assumptions!$C$27))<2000,ROUNDUP((($A19+$F$8)/(Assumptions!$B$10*12*Assumptions!$C$27)),0),IF((($A19+$F$9)/(Assumptions!$B$10*12*Assumptions!$C$27))<10000,ROUNDUP((($A19+$F$9)/(Assumptions!$B$10*12*Assumptions!$C$27)),0),ROUNDUP((($A19+$F$10)/(Assumptions!$B$10*12*Assumptions!$C$27)),0))))),"n/a") -> 17762 | D19: =IFERROR(IF((($A19+$F$6)/(Assumptions!$B$11*12*Assumptions!$C$27))<200,ROUNDUP((($A19+$F$6)/(Assumptions!$B$11*12*Assumptions!$C$27)),0),IF((($A19+$F$7)/(Assumptions!$B$11*12*Assumptions!$C$27))<1000,ROUNDUP((($A19+$F$7)/(Assumptions!$B$11*12*Assumptions!$C$27)),0),IF((($A19+$F$8)/(Assumptions!$B$11*12*Assumptions!$C$27))<2000,ROUNDUP((($A19+$F$8)/(Assumptions!$B$11*12*Assumptions!$C$27)),0),IF((($A19+$F$9)/(Assumptions!$B$11*12*Assumptions!$C$27))<10000,ROUNDUP((($A19+$F$9)/(Assumptions!$B$11*12*Assumptions!$C$27)),0),ROUNDUP((($A19+$F$10)/(Assumptions!$B$11*12*Assumptions!$C$27)),0))))),"n/a") -> 2966 | E19: =IFERROR(IF((($A19+$F$6)/(Assumptions!$B$12*12*Assumptions!$C$27))<200,ROUNDUP((($A19+$F$6)/(Assumptions!$B$12*12*Assumptions!$C$27)),0),IF((($A19+$F$7)/(Assumptions!$B$12*12*Assumptions!$C$27))<1000,ROUNDUP((($A19+$F$7)/(Assumptions!$B$12*12*Assumptions!$C$27)),0),IF((($A19+$F$8)/(Assumptions!$B$12*12*Assumptions!$C$27))<2000,ROUNDUP((($A19+$F$8)/(Assumptions!$B$12*12*Assumptions!$C$27)),0),IF((($A19+$F$9)/(Assumptions!$B$12*12*Assumptions!$C$27))<10000,ROUNDUP((($A19+$F$9)/(Assumptions!$B$12*12*Assumptions!$C$27)),0),ROUNDUP((($A19+$F$10)/(Assumptions!$B$12*12*Assumptions!$C$27)),0))))),"n/a") -> 509
A20: =$B$13 -> 100000 | B20: =Assumptions!$B$28 -> 0.07 | C20: =IFERROR(IF((($A20+$F$6)/(Assumptions!$B$10*12*Assumptions!$C$28))<200,ROUNDUP((($A20+$F$6)/(Assumptions!$B$10*12*Assumptions!$C$28)),0),IF((($A20+$F$7)/(Assumptions!$B$10*12*Assumptions!$C$28))<1000,ROUNDUP((($A20+$F$7)/(Assumptions!$B$10*12*Assumptions!$C$28)),0),IF((($A20+$F$8)/(Assumptions!$B$10*12*Assumptions!$C$28))<2000,ROUNDUP((($A20+$F$8)/(Assumptions!$B$10*12*Assumptions!$C$28)),0),IF((($A20+$F$9)/(Assumptions!$B$10*12*Assumptions!$C$28))<10000,ROUNDUP((($A20+$F$9)/(Assumptions!$B$10*12*Assumptions!$C$28)),0),ROUNDUP((($A20+$F$10)/(Assumptions!$B$10*12*Assumptions!$C$28)),0))))),"n/a") -> 8087 | D20: =IFERROR(IF((($A20+$F$6)/(Assumptions!$B$11*12*Assumptions!$C$28))<200,ROUNDUP((($A20+$F$6)/(Assumptions!$B$11*12*Assumptions!$C$28)),0),IF((($A20+$F$7)/(Assumptions!$B$11*12*Assumptions!$C$28))<1000,ROUNDUP((($A20+$F$7)/(Assumptions!$B$11*12*Assumptions!$C$28)),0),IF((($A20+$F$8)/(Assumptions!$B$11*12*Assumptions!$C$28))<2000,ROUNDUP((($A20+$F$8)/(Assumptions!$B$11*12*Assumptions!$C$28)),0),IF((($A20+$F$9)/(Assumptions!$B$11*12*Assumptions!$C$28))<10000,ROUNDUP((($A20+$F$9)/(Assumptions!$B$11*12*Assumptions!$C$28)),0),ROUNDUP((($A20+$F$10)/(Assumptions!$B$11*12*Assumptions!$C$28)),0))))),"n/a") -> 1246 | E20: =IFERROR(IF((($A20+$F$6)/(Assumptions!$B$12*12*Assumptions!$C$28))<200,ROUNDUP((($A20+$F$6)/(Assumptions!$B$12*12*Assumptions!$C$28)),0),IF((($A20+$F$7)/(Assumptions!$B$12*12*Assumptions!$C$28))<1000,ROUNDUP((($A20+$F$7)/(Assumptions!$B$12*12*Assumptions!$C$28)),0),IF((($A20+$F$8)/(Assumptions!$B$12*12*Assumptions!$C$28))<2000,ROUNDUP((($A20+$F$8)/(Assumptions!$B$12*12*Assumptions!$C$28)),0),IF((($A20+$F$9)/(Assumptions!$B$12*12*Assumptions!$C$28))<10000,ROUNDUP((($A20+$F$9)/(Assumptions!$B$12*12*Assumptions!$C$28)),0),ROUNDUP((($A20+$F$10)/(Assumptions!$B$12*12*Assumptions!$C$28)),0))))),"n/a") -> 172
A21: =$B$13 -> 100000 | B21: =Assumptions!$B$29 -> 0.08 | C21: =IFERROR(IF((($A21+$F$6)/(Assumptions!$B$10*12*Assumptions!$C$29))<200,ROUNDUP((($A21+$F$6)/(Assumptions!$B$10*12*Assumptions!$C$29)),0),IF((($A21+$F$7)/(Assumptions!$B$10*12*Assumptions!$C$29))<1000,ROUNDUP((($A21+$F$7)/(Assumptions!$B$10*12*Assumptions!$C$29)),0),IF((($A21+$F$8)/(Assumptions!$B$10*12*Assumptions!$C$29))<2000,ROUNDUP((($A21+$F$8)/(Assumptions!$B$10*12*Assumptions!$C$29)),0),IF((($A21+$F$9)/(Assumptions!$B$10*12*Assumptions!$C$29))<10000,ROUNDUP((($A21+$F$9)/(Assumptions!$B$10*12*Assumptions!$C$29)),0),ROUNDUP((($A21+$F$10)/(Assumptions!$B$10*12*Assumptions!$C$29)),0))))),"n/a") -> 5777 | D21: =IFERROR(IF((($A21+$F$6)/(Assumptions!$B$11*12*Assumptions!$C$29))<200,ROUNDUP((($A21+$F$6)/(Assumptions!$B$11*12*Assumptions!$C$29)),0),IF((($A21+$F$7)/(Assumptions!$B$11*12*Assumptions!$C$29))<1000,ROUNDUP((($A21+$F$7)/(Assumptions!$B$11*12*Assumptions!$C$29)),0),IF((($A21+$F$8)/(Assumptions!$B$11*12*Assumptions!$C$29))<2000,ROUNDUP((($A21+$F$8)/(Assumptions!$B$11*12*Assumptions!$C$29)),0),IF((($A21+$F$9)/(Assumptions!$B$11*12*Assumptions!$C$29))<10000,ROUNDUP((($A21+$F$9)/(Assumptions!$B$11*12*Assumptions!$C$29)),0),ROUNDUP((($A21+$F$10)/(Assumptions!$B$11*12*Assumptions!$C$29)),0))))),"n/a") -> 873 | E21: =IFERROR(IF((($A21+$F$6)/(Assumptions!$B$12*12*Assumptions!$C$29))<200,ROUNDUP((($A21+$F$6)/(Assumptions!$B$12*12*Assumptions!$C$29)),0),IF((($A21+$F$7)/(Assumptions!$B$12*12*Assumptions!$C$29))<1000,ROUNDUP((($A21+$F$7)/(Assumptions!$B$12*12*Assumptions!$C$29)),0),IF((($A21+$F$8)/(Assumptions!$B$12*12*Assumptions!$C$29))<2000,ROUNDUP((($A21+$F$8)/(Assumptions!$B$12*12*Assumptions!$C$29)),0),IF((($A21+$F$9)/(Assumptions!$B$12*12*Assumptions!$C$29))<10000,ROUNDUP((($A21+$F$9)/(Assumptions!$B$12*12*Assumptions!$C$29)),0),ROUNDUP((($A21+$F$10)/(Assumptions!$B$12*12*Assumptions!$C$29)),0))))),"n/a") -> 123
A22: =$B$13 -> 100000 | B22: =Assumptions!$B$30 -> 0.09 | C22: =IFERROR(IF((($A22+$F$6)/(Assumptions!$B$10*12*Assumptions!$C$30))<200,ROUNDUP((($A22+$F$6)/(Assumptions!$B$10*12*Assumptions!$C$30)),0),IF((($A22+$F$7)/(Assumptions!$B$10*12*Assumptions!$C$30))<1000,ROUNDUP((($A22+$F$7)/(Assumptions!$B$10*12*Assumptions!$C$30)),0),IF((($A22+$F$8)/(Assumptions!$B$10*12*Assumptions!$C$30))<2000,ROUNDUP((($A22+$F$8)/(Assumptions!$B$10*12*Assumptions!$C$30)),0),IF((($A22+$F$9)/(Assumptions!$B$10*12*Assumptions!$C$30))<10000,ROUNDUP((($A22+$F$9)/(Assumptions!$B$10*12*Assumptions!$C$30)),0),ROUNDUP((($A22+$F$10)/(Assumptions!$B$10*12*Assumptions!$C$30)),0))))),"n/a") -> 4493 | D22: =IFERROR(IF((($A22+$F$6)/(Assumptions!$B$11*12*Assumptions!$C$30))<200,ROUNDUP((($A22+$F$6)/(Assumptions!$B$11*12*Assumptions!$C$30)),0),IF((($A22+$F$7)/(Assumptions!$B$11*12*Assumptions!$C$30))<1000,ROUNDUP((($A22+$F$7)/(Assumptions!$B$11*12*Assumptions!$C$30)),0),IF((($A22+$F$8)/(Assumptions!$B$11*12*Assumptions!$C$30))<2000,ROUNDUP((($A22+$F$8)/(Assumptions!$B$11*12*Assumptions!$C$30)),0),IF((($A22+$F$9)/(Assumptions!$B$11*12*Assumptions!$C$30))<10000,ROUNDUP((($A22+$F$9)/(Assumptions!$B$11*12*Assumptions!$C$30)),0),ROUNDUP((($A22+$F$10)/(Assumptions!$B$11*12*Assumptions!$C$30)),0))))),"n/a") -> 679 | E22: =IFERROR(IF((($A22+$F$6)/(Assumptions!$B$12*12*Assumptions!$C$30))<200,ROUNDUP((($A22+$F$6)/(Assumptions!$B$12*12*Assumptions!$C$30)),0),IF((($A22+$F$7)/(Assumptions!$B$12*12*Assumptions!$C$30))<1000,ROUNDUP((($A22+$F$7)/(Assumptions!$B$12*12*Assumptions!$C$30)),0),IF((($A22+$F$8)/(Assumptions!$B$12*12*Assumptions!$C$30))<2000,ROUNDUP((($A22+$F$8)/(Assumptions!$B$12*12*Assumptions!$C$30)),0),IF((($A22+$F$9)/(Assumptions!$B$12*12*Assumptions!$C$30))<10000,ROUNDUP((($A22+$F$9)/(Assumptions!$B$12*12*Assumptions!$C$30)),0),ROUNDUP((($A22+$F$10)/(Assumptions!$B$12*12*Assumptions!$C$30)),0))))),"n/a") -> 96
A23: =$B$14 -> 300000 | B23: =Assumptions!$B$27 -> 0.06 | C23: =IFERROR(IF((($A23+$F$6)/(Assumptions!$B$10*12*Assumptions!$C$27))<200,ROUNDUP((($A23+$F$6)/(Assumptions!$B$10*12*Assumptions!$C$27)),0),IF((($A23+$F$7)/(Assumptions!$B$10*12*Assumptions!$C$27))<1000,ROUNDUP((($A23+$F$7)/(Assumptions!$B$10*12*Assumptions!$C$27)),0),IF((($A23+$F$8)/(Assumptions!$B$10*12*Assumptions!$C$27))<2000,ROUNDUP((($A23+$F$8)/(Assumptions!$B$10*12*Assumptions!$C$27)),0),IF((($A23+$F$9)/(Assumptions!$B$10*12*Assumptions!$C$27))<10000,ROUNDUP((($A23+$F$9)/(Assumptions!$B$10*12*Assumptions!$C$27)),0),ROUNDUP((($A23+$F$10)/(Assumptions!$B$10*12*Assumptions!$C$27)),0))))),"n/a") -> 27863 | D23: =IFERROR(IF((($A23+$F$6)/(Assumptions!$B$11*12*Assumptions!$C$27))<200,ROUNDUP((($A23+$F$6)/(Assumptions!$B$11*12*Assumptions!$C$27)),0),IF((($A23+$F$7)/(Assumptions!$B$11*12*Assumptions!$C$27))<1000,ROUNDUP((($A23+$F$7)/(Assumptions!$B$11*12*Assumptions!$C$27)),0),IF((($A23+$F$8)/(Assumptions!$B$11*12*Assumptions!$C$27))<2000,ROUNDUP((($A23+$F$8)/(Assumptions!$B$11*12*Assumptions!$C$27)),0),IF((($A23+$F$9)/(Assumptions!$B$11*12*Assumptions!$C$27))<10000,ROUNDUP((($A23+$F$9)/(Assumptions!$B$11*12*Assumptions!$C$27)),0),ROUNDUP((($A23+$F$10)/(Assumptions!$B$11*12*Assumptions!$C$27)),0))))),"n/a") -> 5188 | E23: =IFERROR(IF((($A23+$F$6)/(Assumptions!$B$12*12*Assumptions!$C$27))<200,ROUNDUP((($A23+$F$6)/(Assumptions!$B$12*12*Assumptions!$C$27)),0),IF((($A23+$F$7)/(Assumptions!$B$12*12*Assumptions!$C$27))<1000,ROUNDUP((($A23+$F$7)/(Assumptions!$B$12*12*Assumptions!$C$27)),0),IF((($A23+$F$8)/(Assumptions!$B$12*12*Assumptions!$C$27))<2000,ROUNDUP((($A23+$F$8)/(Assumptions!$B$12*12*Assumptions!$C$27)),0),IF((($A23+$F$9)/(Assumptions!$B$12*12*Assumptions!$C$27))<10000,ROUNDUP((($A23+$F$9)/(Assumptions!$B$12*12*Assumptions!$C$27)),0),ROUNDUP((($A23+$F$10)/(Assumptions!$B$12*12*Assumptions!$C$27)),0))))),"n/a") -> 1075
A24: =$B$14 -> 300000 | B24: =Assumptions!$B$28 -> 0.07 | C24: =IFERROR(IF((($A24+$F$6)/(Assumptions!$B$10*12*Assumptions!$C$28))<200,ROUNDUP((($A24+$F$6)/(Assumptions!$B$10*12*Assumptions!$C$28)),0),IF((($A24+$F$7)/(Assumptions!$B$10*12*Assumptions!$C$28))<1000,ROUNDUP((($A24+$F$7)/(Assumptions!$B$10*12*Assumptions!$C$28)),0),IF((($A24+$F$8)/(Assumptions!$B$10*12*Assumptions!$C$28))<2000,ROUNDUP((($A24+$F$8)/(Assumptions!$B$10*12*Assumptions!$C$28)),0),IF((($A24+$F$9)/(Assumptions!$B$10*12*Assumptions!$C$28))<10000,ROUNDUP((($A24+$F$9)/(Assumptions!$B$10*12*Assumptions!$C$28)),0),ROUNDUP((($A24+$F$10)/(Assumptions!$B$10*12*Assumptions!$C$28)),0))))),"n/a") -> 16718 | D24: =IFERROR(IF((($A24+$F$6)/(Assumptions!$B$11*12*Assumptions!$C$28))<200,ROUNDUP((($A24+$F$6)/(Assumptions!$B$11*12*Assumptions!$C$28)),0),IF((($A24+$F$7)/(Assumptions!$B$11*12*Assumptions!$C$28))<1000,ROUNDUP((($A24+$F$7)/(Assumptions!$B$11*12*Assumptions!$C$28)),0),IF((($A24+$F$8)/(Assumptions!$B$11*12*Assumptions!$C$28))<2000,ROUNDUP((($A24+$F$8)/(Assumptions!$B$11*12*Assumptions!$C$28)),0),IF((($A24+$F$9)/(Assumptions!$B$11*12*Assumptions!$C$28))<10000,ROUNDUP((($A24+$F$9)/(Assumptions!$B$11*12*Assumptions!$C$28)),0),ROUNDUP((($A24+$F$10)/(Assumptions!$B$11*12*Assumptions!$C$28)),0))))),"n/a") -> 3113 | E24: =IFERROR(IF((($A24+$F$6)/(Assumptions!$B$12*12*Assumptions!$C$28))<200,ROUNDUP((($A24+$F$6)/(Assumptions!$B$12*12*Assumptions!$C$28)),0),IF((($A24+$F$7)/(Assumptions!$B$12*12*Assumptions!$C$28))<1000,ROUNDUP((($A24+$F$7)/(Assumptions!$B$12*12*Assumptions!$C$28)),0),IF((($A24+$F$8)/(Assumptions!$B$12*12*Assumptions!$C$28))<2000,ROUNDUP((($A24+$F$8)/(Assumptions!$B$12*12*Assumptions!$C$28)),0),IF((($A24+$F$9)/(Assumptions!$B$12*12*Assumptions!$C$28))<10000,ROUNDUP((($A24+$F$9)/(Assumptions!$B$12*12*Assumptions!$C$28)),0),ROUNDUP((($A24+$F$10)/(Assumptions!$B$12*12*Assumptions!$C$28)),0))))),"n/a") -> 639
A25: =$B$14 -> 300000 | B25: =Assumptions!$B$29 -> 0.08 | C25: =IFERROR(IF((($A25+$F$6)/(Assumptions!$B$10*12*Assumptions!$C$29))<200,ROUNDUP((($A25+$F$6)/(Assumptions!$B$10*12*Assumptions!$C$29)),0),IF((($A25+$F$7)/(Assumptions!$B$10*12*Assumptions!$C$29))<1000,ROUNDUP((($A25+$F$7)/(Assumptions!$B$10*12*Assumptions!$C$29)),0),IF((($A25+$F$8)/(Assumptions!$B$10*12*Assumptions!$C$29))<2000,ROUNDUP((($A25+$F$8)/(Assumptions!$B$10*12*Assumptions!$C$29)),0),IF((($A25+$F$9)/(Assumptions!$B$10*12*Assumptions!$C$29))<10000,ROUNDUP((($A25+$F$9)/(Assumptions!$B$10*12*Assumptions!$C$29)),0),ROUNDUP((($A25+$F$10)/(Assumptions!$B$10*12*Assumptions!$C$29)),0))))),"n/a") -> 11941 | D25: =IFERROR(IF((($A25+$F$6)/(Assumptions!$B$11*12*Assumptions!$C$29))<200,ROUNDUP((($A25+$F$6)/(Assumptions!$B$11*12*Assumptions!$C$29)),0),IF((($A25+$F$7)/(Assumptions!$B$11*12*Assumptions!$C$29))<1000,ROUNDUP((($A25+$F$7)/(Assumptions!$B$11*12*Assumptions!$C$29)),0),IF((($A25+$F$8)/(Assumptions!$B$11*12*Assumptions!$C$29))<2000,ROUNDUP((($A25+$F$8)/(Assumptions!$B$11*12*Assumptions!$C$29)),0),IF((($A25+$F$9)/(Assumptions!$B$11*12*Assumptions!$C$29))<10000,ROUNDUP((($A25+$F$9)/(Assumptions!$B$11*12*Assumptions!$C$29)),0),ROUNDUP((($A25+$F$10)/(Assumptions!$B$11*12*Assumptions!$C$29)),0))))),"n/a") -> 1843 | E25: =IFERROR(IF((($A25+$F$6)/(Assumptions!$B$12*12*Assumptions!$C$29))<200,ROUNDUP((($A25+$F$6)/(Assumptions!$B$12*12*Assumptions!$C$29)),0),IF((($A25+$F$7)/(Assumptions!$B$12*12*Assumptions!$C$29))<1000,ROUNDUP((($A25+$F$7)/(Assumptions!$B$12*12*Assumptions!$C$29)),0),IF((($A25+$F$8)/(Assumptions!$B$12*12*Assumptions!$C$29))<2000,ROUNDUP((($A25+$F$8)/(Assumptions!$B$12*12*Assumptions!$C$29)),0),IF((($A25+$F$9)/(Assumptions!$B$12*12*Assumptions!$C$29))<10000,ROUNDUP((($A25+$F$9)/(Assumptions!$B$12*12*Assumptions!$C$29)),0),ROUNDUP((($A25+$F$10)/(Assumptions!$B$12*12*Assumptions!$C$29)),0))))),"n/a") -> 457
A26: =$B$14 -> 300000 | B26: =Assumptions!$B$30 -> 0.09 | C26: =IFERROR(IF((($A26+$F$6)/(Assumptions!$B$10*12*Assumptions!$C$30))<200,ROUNDUP((($A26+$F$6)/(Assumptions!$B$10*12*Assumptions!$C$30)),0),IF((($A26+$F$7)/(Assumptions!$B$10*12*Assumptions!$C$30))<1000,ROUNDUP((($A26+$F$7)/(Assumptions!$B$10*12*Assumptions!$C$30)),0),IF((($A26+$F$8)/(Assumptions!$B$10*12*Assumptions!$C$30))<2000,ROUNDUP((($A26+$F$8)/(Assumptions!$B$10*12*Assumptions!$C$30)),0),IF((($A26+$F$9)/(Assumptions!$B$10*12*Assumptions!$C$30))<10000,ROUNDUP((($A26+$F$9)/(Assumptions!$B$10*12*Assumptions!$C$30)),0),ROUNDUP((($A26+$F$10)/(Assumptions!$B$10*12*Assumptions!$C$30)),0))))),"n/a") -> 7860 | D26: =IFERROR(IF((($A26+$F$6)/(Assumptions!$B$11*12*Assumptions!$C$30))<200,ROUNDUP((($A26+$F$6)/(Assumptions!$B$11*12*Assumptions!$C$30)),0),IF((($A26+$F$7)/(Assumptions!$B$11*12*Assumptions!$C$30))<1000,ROUNDUP((($A26+$F$7)/(Assumptions!$B$11*12*Assumptions!$C$30)),0),IF((($A26+$F$8)/(Assumptions!$B$11*12*Assumptions!$C$30))<2000,ROUNDUP((($A26+$F$8)/(Assumptions!$B$11*12*Assumptions!$C$30)),0),IF((($A26+$F$9)/(Assumptions!$B$11*12*Assumptions!$C$30))<10000,ROUNDUP((($A26+$F$9)/(Assumptions!$B$11*12*Assumptions!$C$30)),0),ROUNDUP((($A26+$F$10)/(Assumptions!$B$11*12*Assumptions!$C$30)),0))))),"n/a") -> 1433 | E26: =IFERROR(IF((($A26+$F$6)/(Assumptions!$B$12*12*Assumptions!$C$30))<200,ROUNDUP((($A26+$F$6)/(Assumptions!$B$12*12*Assumptions!$C$30)),0),IF((($A26+$F$7)/(Assumptions!$B$12*12*Assumptions!$C$30))<1000,ROUNDUP((($A26+$F$7)/(Assumptions!$B$12*12*Assumptions!$C$30)),0),IF((($A26+$F$8)/(Assumptions!$B$12*12*Assumptions!$C$30))<2000,ROUNDUP((($A26+$F$8)/(Assumptions!$B$12*12*Assumptions!$C$30)),0),IF((($A26+$F$9)/(Assumptions!$B$12*12*Assumptions!$C$30))<10000,ROUNDUP((($A26+$F$9)/(Assumptions!$B$12*12*Assumptions!$C$30)),0),ROUNDUP((($A26+$F$10)/(Assumptions!$B$12*12*Assumptions!$C$30)),0))))),"n/a") -> 355
A27: =$B$15 -> 500000 | B27: =Assumptions!$B$27 -> 0.06 | C27: =IFERROR(IF((($A27+$F$6)/(Assumptions!$B$10*12*Assumptions!$C$27))<200,ROUNDUP((($A27+$F$6)/(Assumptions!$B$10*12*Assumptions!$C$27)),0),IF((($A27+$F$7)/(Assumptions!$B$10*12*Assumptions!$C$27))<1000,ROUNDUP((($A27+$F$7)/(Assumptions!$B$10*12*Assumptions!$C$27)),0),IF((($A27+$F$8)/(Assumptions!$B$10*12*Assumptions!$C$27))<2000,ROUNDUP((($A27+$F$8)/(Assumptions!$B$10*12*Assumptions!$C$27)),0),IF((($A27+$F$9)/(Assumptions!$B$10*12*Assumptions!$C$27))<10000,ROUNDUP((($A27+$F$9)/(Assumptions!$B$10*12*Assumptions!$C$27)),0),ROUNDUP((($A27+$F$10)/(Assumptions!$B$10*12*Assumptions!$C$27)),0))))),"n/a") -> 37964 | D27: =IFERROR(IF((($A27+$F$6)/(Assumptions!$B$11*12*Assumptions!$C$27))<200,ROUNDUP((($A27+$F$6)/(Assumptions!$B$11*12*Assumptions!$C$27)),0),IF((($A27+$F$7)/(Assumptions!$B$11*12*Assumptions!$C$27))<1000,ROUNDUP((($A27+$F$7)/(Assumptions!$B$11*12*Assumptions!$C$27)),0),IF((($A27+$F$8)/(Assumptions!$B$11*12*Assumptions!$C$27))<2000,ROUNDUP((($A27+$F$8)/(Assumptions!$B$11*12*Assumptions!$C$27)),0),IF((($A27+$F$9)/(Assumptions!$B$11*12*Assumptions!$C$27))<10000,ROUNDUP((($A27+$F$9)/(Assumptions!$B$11*12*Assumptions!$C$27)),0),ROUNDUP((($A27+$F$10)/(Assumptions!$B$11*12*Assumptions!$C$27)),0))))),"n/a") -> 7410 | E27: =IFERROR(IF((($A27+$F$6)/(Assumptions!$B$12*12*Assumptions!$C$27))<200,ROUNDUP((($A27+$F$6)/(Assumptions!$B$12*12*Assumptions!$C$27)),0),IF((($A27+$F$7)/(Assumptions!$B$12*12*Assumptions!$C$27))<1000,ROUNDUP((($A27+$F$7)/(Assumptions!$B$12*12*Assumptions!$C$27)),0),IF((($A27+$F$8)/(Assumptions!$B$12*12*Assumptions!$C$27))<2000,ROUNDUP((($A27+$F$8)/(Assumptions!$B$12*12*Assumptions!$C$27)),0),IF((($A27+$F$9)/(Assumptions!$B$12*12*Assumptions!$C$27))<10000,ROUNDUP((($A27+$F$9)/(Assumptions!$B$12*12*Assumptions!$C$27)),0),ROUNDUP((($A27+$F$10)/(Assumptions!$B$12*12*Assumptions!$C$27)),0))))),"n/a") -> 1631
A28: =$B$15 -> 500000 | B28: =Assumptions!$B$28 -> 0.07 | C28: =IFERROR(IF((($A28+$F$6)/(Assumptions!$B$10*12*Assumptions!$C$28))<200,ROUNDUP((($A28+$F$6)/(Assumptions!$B$10*12*Assumptions!$C$28)),0),IF((($A28+$F$7)/(Assumptions!$B$10*12*Assumptions!$C$28))<1000,ROUNDUP((($A28+$F$7)/(Assumptions!$B$10*12*Assumptions!$C$28)),0),IF((($A28+$F$8)/(Assumptions!$B$10*12*Assumptions!$C$28))<2000,ROUNDUP((($A28+$F$8)/(Assumptions!$B$10*12*Assumptions!$C$28)),0),IF((($A28+$F$9)/(Assumptions!$B$10*12*Assumptions!$C$28))<10000,ROUNDUP((($A28+$F$9)/(Assumptions!$B$10*12*Assumptions!$C$28)),0),ROUNDUP((($A28+$F$10)/(Assumptions!$B$10*12*Assumptions!$C$28)),0))))),"n/a") -> 22778 | D28: =IFERROR(IF((($A28+$F$6)/(Assumptions!$B$11*12*Assumptions!$C$28))<200,ROUNDUP((($A28+$F$6)/(Assumptions!$B$11*12*Assumptions!$C$28)),0),IF((($A28+$F$7)/(Assumptions!$B$11*12*Assumptions!$C$28))<1000,ROUNDUP((($A28+$F$7)/(Assumptions!$B$11*12*Assumptions!$C$28)),0),IF((($A28+$F$8)/(Assumptions!$B$11*12*Assumptions!$C$28))<2000,ROUNDUP((($A28+$F$8)/(Assumptions!$B$11*12*Assumptions!$C$28)),0),IF((($A28+$F$9)/(Assumptions!$B$11*12*Assumptions!$C$28))<10000,ROUNDUP((($A28+$F$9)/(Assumptions!$B$11*12*Assumptions!$C$28)),0),ROUNDUP((($A28+$F$10)/(Assumptions!$B$11*12*Assumptions!$C$28)),0))))),"n/a") -> 4446 | E28: =IFERROR(IF((($A28+$F$6)/(Assumptions!$B$12*12*Assumptions!$C$28))<200,ROUNDUP((($A28+$F$6)/(Assumptions!$B$12*12*Assumptions!$C$28)),0),IF((($A28+$F$7)/(Assumptions!$B$12*12*Assumptions!$C$28))<1000,ROUNDUP((($A28+$F$7)/(Assumptions!$B$12*12*Assumptions!$C$28)),0),IF((($A28+$F$8)/(Assumptions!$B$12*12*Assumptions!$C$28))<2000,ROUNDUP((($A28+$F$8)/(Assumptions!$B$12*12*Assumptions!$C$28)),0),IF((($A28+$F$9)/(Assumptions!$B$12*12*Assumptions!$C$28))<10000,ROUNDUP((($A28+$F$9)/(Assumptions!$B$12*12*Assumptions!$C$28)),0),ROUNDUP((($A28+$F$10)/(Assumptions!$B$12*12*Assumptions!$C$28)),0))))),"n/a") -> 972
A29: =$B$15 -> 500000 | B29: =Assumptions!$B$29 -> 0.08 | C29: =IFERROR(IF((($A29+$F$6)/(Assumptions!$B$10*12*Assumptions!$C$29))<200,ROUNDUP((($A29+$F$6)/(Assumptions!$B$10*12*Assumptions!$C$29)),0),IF((($A29+$F$7)/(Assumptions!$B$10*12*Assumptions!$C$29))<1000,ROUNDUP((($A29+$F$7)/(Assumptions!$B$10*12*Assumptions!$C$29)),0),IF((($A29+$F$8)/(Assumptions!$B$10*12*Assumptions!$C$29))<2000,ROUNDUP((($A29+$F$8)/(Assumptions!$B$10*12*Assumptions!$C$29)),0),IF((($A29+$F$9)/(Assumptions!$B$10*12*Assumptions!$C$29))<10000,ROUNDUP((($A29+$F$9)/(Assumptions!$B$10*12*Assumptions!$C$29)),0),ROUNDUP((($A29+$F$10)/(Assumptions!$B$10*12*Assumptions!$C$29)),0))))),"n/a") -> 16270 | D29: =IFERROR(IF((($A29+$F$6)/(Assumptions!$B$11*12*Assumptions!$C$29))<200,ROUNDUP((($A29+$F$6)/(Assumptions!$B$11*12*Assumptions!$C$29)),0),IF((($A29+$F$7)/(Assumptions!$B$11*12*Assumptions!$C$29))<1000,ROUNDUP((($A29+$F$7)/(Assumptions!$B$11*12*Assumptions!$C$29)),0),IF((($A29+$F$8)/(Assumptions!$B$11*12*Assumptions!$C$29))<2000,ROUNDUP((($A29+$F$8)/(Assumptions!$B$11*12*Assumptions!$C$29)),0),IF((($A29+$F$9)/(Assumptions!$B$11*12*Assumptions!$C$29))<10000,ROUNDUP((($A29+$F$9)/(Assumptions!$B$11*12*Assumptions!$C$29)),0),ROUNDUP((($A29+$F$10)/(Assumptions!$B$11*12*Assumptions!$C$29)),0))))),"n/a") -> 3176 | E29: =IFERROR(IF((($A29+$F$6)/(Assumptions!$B$12*12*Assumptions!$C$29))<200,ROUNDUP((($A29+$F$6)/(Assumptions!$B$12*12*Assumptions!$C$29)),0),IF((($A29+$F$7)/(Assumptions!$B$12*12*Assumptions!$C$29))<1000,ROUNDUP((($A29+$F$7)/(Assumptions!$B$12*12*Assumptions!$C$29)),0),IF((($A29+$F$8)/(Assumptions!$B$12*12*Assumptions!$C$29))<2000,ROUNDUP((($A29+$F$8)/(Assumptions!$B$12*12*Assumptions!$C$29)),0),IF((($A29+$F$9)/(Assumptions!$B$12*12*Assumptions!$C$29))<10000,ROUNDUP((($A29+$F$9)/(Assumptions!$B$12*12*Assumptions!$C$29)),0),ROUNDUP((($A29+$F$10)/(Assumptions!$B$12*12*Assumptions!$C$29)),0))))),"n/a") -> 695
A30: =$B$15 -> 500000 | B30: =Assumptions!$B$30 -> 0.09 | C30: =IFERROR(IF((($A30+$F$6)/(Assumptions!$B$10*12*Assumptions!$C$30))<200,ROUNDUP((($A30+$F$6)/(Assumptions!$B$10*12*Assumptions!$C$30)),0),IF((($A30+$F$7)/(Assumptions!$B$10*12*Assumptions!$C$30))<1000,ROUNDUP((($A30+$F$7)/(Assumptions!$B$10*12*Assumptions!$C$30)),0),IF((($A30+$F$8)/(Assumptions!$B$10*12*Assumptions!$C$30))<2000,ROUNDUP((($A30+$F$8)/(Assumptions!$B$10*12*Assumptions!$C$30)),0),IF((($A30+$F$9)/(Assumptions!$B$10*12*Assumptions!$C$30))<10000,ROUNDUP((($A30+$F$9)/(Assumptions!$B$10*12*Assumptions!$C$30)),0),ROUNDUP((($A30+$F$10)/(Assumptions!$B$10*12*Assumptions!$C$30)),0))))),"n/a") -> 12655 | D30: =IFERROR(IF((($A30+$F$6)/(Assumptions!$B$11*12*Assumptions!$C$30))<200,ROUNDUP((($A30+$F$6)/(Assumptions!$B$11*12*Assumptions!$C$30)),0),IF((($A30+$F$7)/(Assumptions!$B$11*12*Assumptions!$C$30))<1000,ROUNDUP((($A30+$F$7)/(Assumptions!$B$11*12*Assumptions!$C$30)),0),IF((($A30+$F$8)/(Assumptions!$B$11*12*Assumptions!$C$30))<2000,ROUNDUP((($A30+$F$8)/(Assumptions!$B$11*12*Assumptions!$C$30)),0),IF((($A30+$F$9)/(Assumptions!$B$11*12*Assumptions!$C$30))<10000,ROUNDUP((($A30+$F$9)/(Assumptions!$B$11*12*Assumptions!$C$30)),0),ROUNDUP((($A30+$F$10)/(Assumptions!$B$11*12*Assumptions!$C$30)),0))))),"n/a") -> 2470 | E30: =IFERROR(IF((($A30+$F$6)/(Assumptions!$B$12*12*Assumptions!$C$30))<200,ROUNDUP((($A30+$F$6)/(Assumptions!$B$12*12*Assumptions!$C$30)),0),IF((($A30+$F$7)/(Assumptions!$B$12*12*Assumptions!$C$30))<1000,ROUNDUP((($A30+$F$7)/(Assumptions!$B$12*12*Assumptions!$C$30)),0),IF((($A30+$F$8)/(Assumptions!$B$12*12*Assumptions!$C$30))<2000,ROUNDUP((($A30+$F$8)/(Assumptions!$B$12*12*Assumptions!$C$30)),0),IF((($A30+$F$9)/(Assumptions!$B$12*12*Assumptions!$C$30))<10000,ROUNDUP((($A30+$F$9)/(Assumptions!$B$12*12*Assumptions!$C$30)),0),ROUNDUP((($A30+$F$10)/(Assumptions!$B$12*12*Assumptions!$C$30)),0))))),"n/a") -> 540
A32: Jumps between fee tiers are hiring steps. A fee cut that pushes you past a hire threshold costs an $80,000 salary, not just the fee points.
A35: TABLE B - MONTHLY GMV PER SELLER REQUIRED, at fixed seller counts
A36: Profit target | B36: Fee | C36: 10 sellers | D36: 100 sellers | E36: 1,000 sellers | F36: 10,000 sellers
A37: =$B$13 -> 100000 | B37: =Assumptions!$B$27 -> 0.06 | C37: =IFERROR(($A37+$F$6)/(Assumptions!$B$33*12*Assumptions!$C$27),0) -> 57299.289 | D37: =IFERROR(($A37+$F$6)/(Assumptions!$B$34*12*Assumptions!$C$27),0) -> 5729.9289 | E37: =IFERROR(($A37+$F$8)/(Assumptions!$B$35*12*Assumptions!$C$27),0) -> 1038.1707 | F37: =IFERROR(($A37+$F$10)/(Assumptions!$B$36*12*Assumptions!$C$27),0) -> 195.37262
A38: =$B$13 -> 100000 | B38: =Assumptions!$B$28 -> 0.07 | C38: =IFERROR(($A38+$F$6)/(Assumptions!$B$33*12*Assumptions!$C$28),0) -> 34379.573 | D38: =IFERROR(($A38+$F$6)/(Assumptions!$B$34*12*Assumptions!$C$28),0) -> 3437.9573 | E38: =IFERROR(($A38+$F$8)/(Assumptions!$B$35*12*Assumptions!$C$28),0) -> 622.9024 | F38: =IFERROR(($A38+$F$10)/(Assumptions!$B$36*12*Assumptions!$C$28),0) -> 117.22357
A39: =$B$13 -> 100000 | B39: =Assumptions!$B$29 -> 0.08 | C39: =IFERROR(($A39+$F$6)/(Assumptions!$B$33*12*Assumptions!$C$29),0) -> 24556.838 | D39: =IFERROR(($A39+$F$6)/(Assumptions!$B$34*12*Assumptions!$C$29),0) -> 2455.6838 | E39: =IFERROR(($A39+$F$8)/(Assumptions!$B$35*12*Assumptions!$C$29),0) -> 444.93029 | F39: =IFERROR(($A39+$F$10)/(Assumptions!$B$36*12*Assumptions!$C$29),0) -> 83.731124
A40: =$B$13 -> 100000 | B40: =Assumptions!$B$30 -> 0.09 | C40: =IFERROR(($A40+$F$6)/(Assumptions!$B$33*12*Assumptions!$C$30),0) -> 19099.763 | D40: =IFERROR(($A40+$F$6)/(Assumptions!$B$34*12*Assumptions!$C$30),0) -> 1909.9763 | E40: =IFERROR(($A40+$F$8)/(Assumptions!$B$35*12*Assumptions!$C$30),0) -> 346.05689 | F40: =IFERROR(($A40+$F$10)/(Assumptions!$B$36*12*Assumptions!$C$30),0) -> 65.124207
A41: =$B$14 -> 300000 | B41: =Assumptions!$B$27 -> 0.06 | C41: =IFERROR(($A41+$F$6)/(Assumptions!$B$33*12*Assumptions!$C$27),0) -> 168410.4 | D41: =IFERROR(($A41+$F$6)/(Assumptions!$B$34*12*Assumptions!$C$27),0) -> 16841.04 | E41: =IFERROR(($A41+$F$8)/(Assumptions!$B$35*12*Assumptions!$C$27),0) -> 2149.2818 | F41: =IFERROR(($A41+$F$10)/(Assumptions!$B$36*12*Assumptions!$C$27),0) -> 306.48373
A42: =$B$14 -> 300000 | B42: =Assumptions!$B$28 -> 0.07 | C42: =IFERROR(($A42+$F$6)/(Assumptions!$B$33*12*Assumptions!$C$28),0) -> 101046.24 | D42: =IFERROR(($A42+$F$6)/(Assumptions!$B$34*12*Assumptions!$C$28),0) -> 10104.624 | E42: =IFERROR(($A42+$F$8)/(Assumptions!$B$35*12*Assumptions!$C$28),0) -> 1289.5691 | F42: =IFERROR(($A42+$F$10)/(Assumptions!$B$36*12*Assumptions!$C$28),0) -> 183.89024
A43: =$B$14 -> 300000 | B43: =Assumptions!$B$29 -> 0.08 | C43: =IFERROR(($A43+$F$6)/(Assumptions!$B$33*12*Assumptions!$C$29),0) -> 72175.886 | D43: =IFERROR(($A43+$F$6)/(Assumptions!$B$34*12*Assumptions!$C$29),0) -> 7217.5886 | E43: =IFERROR(($A43+$F$8)/(Assumptions!$B$35*12*Assumptions!$C$29),0) -> 921.12076 | F43: =IFERROR(($A43+$F$10)/(Assumptions!$B$36*12*Assumptions!$C$29),0) -> 131.35017
A44: =$B$14 -> 300000 | B44: =Assumptions!$B$30 -> 0.09 | C44: =IFERROR(($A44+$F$6)/(Assumptions!$B$33*12*Assumptions!$C$30),0) -> 56136.8 | D44: =IFERROR(($A44+$F$6)/(Assumptions!$B$34*12*Assumptions!$C$30),0) -> 5613.68 | E44: =IFERROR(($A44+$F$8)/(Assumptions!$B$35*12*Assumptions!$C$30),0) -> 716.42726 | F44: =IFERROR(($A44+$F$10)/(Assumptions!$B$36*12*Assumptions!$C$30),0) -> 102.16124
A45: =$B$15 -> 500000 | B45: =Assumptions!$B$27 -> 0.06 | C45: =IFERROR(($A45+$F$6)/(Assumptions!$B$33*12*Assumptions!$C$27),0) -> 279521.51 | D45: =IFERROR(($A45+$F$6)/(Assumptions!$B$34*12*Assumptions!$C$27),0) -> 27952.151 | E45: =IFERROR(($A45+$F$8)/(Assumptions!$B$35*12*Assumptions!$C$27),0) -> 3260.3929 | F45: =IFERROR(($A45+$F$10)/(Assumptions!$B$36*12*Assumptions!$C$27),0) -> 417.59484
A46: =$B$15 -> 500000 | B46: =Assumptions!$B$28 -> 0.07 | C46: =IFERROR(($A46+$F$6)/(Assumptions!$B$33*12*Assumptions!$C$28),0) -> 167712.91 | D46: =IFERROR(($A46+$F$6)/(Assumptions!$B$34*12*Assumptions!$C$28),0) -> 16771.291 | E46: =IFERROR(($A46+$F$8)/(Assumptions!$B$35*12*Assumptions!$C$28),0) -> 1956.2357 | F46: =IFERROR(($A46+$F$10)/(Assumptions!$B$36*12*Assumptions!$C$28),0) -> 250.55691
A47: =$B$15 -> 500000 | B47: =Assumptions!$B$29 -> 0.08 | C47: =IFERROR(($A47+$F$6)/(Assumptions!$B$33*12*Assumptions!$C$29),0) -> 119794.93 | D47: =IFERROR(($A47+$F$6)/(Assumptions!$B$34*12*Assumptions!$C$29),0) -> 11979.493 | E47: =IFERROR(($A47+$F$8)/(Assumptions!$B$35*12*Assumptions!$C$29),0) -> 1397.3112 | F47: =IFERROR(($A47+$F$10)/(Assumptions!$B$36*12*Assumptions!$C$29),0) -> 178.96922
A48: =$B$15 -> 500000 | B48: =Assumptions!$B$30 -> 0.09 | C48: =IFERROR(($A48+$F$6)/(Assumptions!$B$33*12*Assumptions!$C$30),0) -> 93173.837 | D48: =IFERROR(($A48+$F$6)/(Assumptions!$B$34*12*Assumptions!$C$30),0) -> 9317.3837 | E48: =IFERROR(($A48+$F$8)/(Assumptions!$B$35*12*Assumptions!$C$30),0) -> 1086.7976 | F48: =IFERROR(($A48+$F$10)/(Assumptions!$B$36*12*Assumptions!$C$30),0) -> 139.19828
A50: The 10-seller column is not a business - it shows the shape of the curve. The 10,000-seller column is the finding: at 8% each seller needs only ~$130/mo to clear $300,000.
A53: TABLE C - THE THREE TARGETS AT 8%, MID BAND
A54: Target | B54: Sellers | C54: Platform GMV | D54: Net revenue | E54: Software | F54: Labour | G54: Profit | H54: Retained | I54: Distributed
A55: =$B$13 -> 100000 | B55: =D21 -> 873 | C55: =B55*Assumptions!$B$11*12 -> 5238000 | D55: =C55*Assumptions!$C$29 -> 183330 | E55: =IF(B55>=10000,11670.72,IF(B55>=1000,6870.72,3138.72)) -> 3138.72 | F55: =Assumptions!$B$19*IF(B55>=Assumptions!$B$22,3,IF(B55>=Assumptions!$B$21,2,IF(B55>=Assumptions!$B$20,1,0))) -> 80000 | G55: =D55-E55-F55 -> 100191.28 | H55: =IF(G55>0,G55*Assumptions!$B$23,G55) -> 50095.64 | I55: =IF(G55>0,G55*(1-Assumptions!$B$23),0) -> 50095.64
A56: =$B$14 -> 300000 | B56: =D25 -> 1843 | C56: =B56*Assumptions!$B$11*12 -> 11058000 | D56: =C56*Assumptions!$C$29 -> 387030 | E56: =IF(B56>=10000,11670.72,IF(B56>=1000,6870.72,3138.72)) -> 6870.72 | F56: =Assumptions!$B$19*IF(B56>=Assumptions!$B$22,3,IF(B56>=Assumptions!$B$21,2,IF(B56>=Assumptions!$B$20,1,0))) -> 80000 | G56: =D56-E56-F56 -> 300159.28 | H56: =IF(G56>0,G56*Assumptions!$B$23,G56) -> 150079.64 | I56: =IF(G56>0,G56*(1-Assumptions!$B$23),0) -> 150079.64
A57: =$B$15 -> 500000 | B57: =D29 -> 3176 | C57: =B57*Assumptions!$B$11*12 -> 19056000 | D57: =C57*Assumptions!$C$29 -> 666960 | E57: =IF(B57>=10000,11670.72,IF(B57>=1000,6870.72,3138.72)) -> 6870.72 | F57: =Assumptions!$B$19*IF(B57>=Assumptions!$B$22,3,IF(B57>=Assumptions!$B$21,2,IF(B57>=Assumptions!$B$20,1,0))) -> 160000 | G57: =D57-E57-F57 -> 500089.28 | H57: =IF(G57>0,G57*Assumptions!$B$23,G57) -> 250044.64 | I57: =IF(G57>0,G57*(1-Assumptions!$B$23),0) -> 250044.64

Sheet 10K Scenario
A1: The 10,000-Seller Scenario — critical mass
A2: Your thesis: 10,000 sellers is the threshold for attracting buyers. The model supports it financially. At 10,000 sellers the platform carries its full cost load: 3 support staff plus $11,671 of software.
A4: 1. PROFIT AT 10,000 SELLERS, by fee and GMV band (base loss rate)
A5: GMV/seller/mo | B5: Fee | C5: Annual GMV | D5: Gross fee rev | E5: Processing | F5: Loss | G5: Net revenue | H5: Operating cost | I5: Profit | J5: Retained | K5: Distributed | L5: Sellers fundable at CAC
A6: =Assumptions!$B$10 -> 110 | B6: =Assumptions!$B$27 -> 0.06 | C6: =A6*Assumptions!$B$36*12 -> 13200000 | D6: =C6*B6 -> 792000 | E6: =-(C6*Assumptions!$B$14+IFERROR(C6/Assumptions!$B$13,0)*Assumptions!$B$15) -> -462000 | F6: =-C6*Assumptions!$B$17 -> -132000 | G6: =D6+E6+F6 -> 198000 | H6: =-Costs!$E$19 -> -251670.72 | I6: =G6+H6 -> -53670.72 | J6: =IF(I6>0,I6*Assumptions!$B$23,I6) -> -53670.72 | K6: =IF(I6>0,I6*(1-Assumptions!$B$23),0) -> 0 | L6: =IFERROR(MAX(J6,0)/Assumptions!$B$24,0) -> 0
A7: =Assumptions!$B$10 -> 110 | B7: =Assumptions!$B$28 -> 0.07 | C7: =A7*Assumptions!$B$36*12 -> 13200000 | D7: =C7*B7 -> 924000 | E7: =-(C7*Assumptions!$B$14+IFERROR(C7/Assumptions!$B$13,0)*Assumptions!$B$15) -> -462000 | F7: =-C7*Assumptions!$B$17 -> -132000 | G7: =D7+E7+F7 -> 330000 | H7: =-Costs!$E$19 -> -251670.72 | I7: =G7+H7 -> 78329.28 | J7: =IF(I7>0,I7*Assumptions!$B$23,I7) -> 39164.64 | K7: =IF(I7>0,I7*(1-Assumptions!$B$23),0) -> 39164.64 | L7: =IFERROR(MAX(J7,0)/Assumptions!$B$24,0) -> 783.2928
A8: =Assumptions!$B$10 -> 110 | B8: =Assumptions!$B$29 -> 0.08 | C8: =A8*Assumptions!$B$36*12 -> 13200000 | D8: =C8*B8 -> 1056000 | E8: =-(C8*Assumptions!$B$14+IFERROR(C8/Assumptions!$B$13,0)*Assumptions!$B$15) -> -462000 | F8: =-C8*Assumptions!$B$17 -> -132000 | G8: =D8+E8+F8 -> 462000 | H8: =-Costs!$E$19 -> -251670.72 | I8: =G8+H8 -> 210329.28 | J8: =IF(I8>0,I8*Assumptions!$B$23,I8) -> 105164.64 | K8: =IF(I8>0,I8*(1-Assumptions!$B$23),0) -> 105164.64 | L8: =IFERROR(MAX(J8,0)/Assumptions!$B$24,0) -> 2103.2928
A9: =Assumptions!$B$10 -> 110 | B9: =Assumptions!$B$30 -> 0.09 | C9: =A9*Assumptions!$B$36*12 -> 13200000 | D9: =C9*B9 -> 1188000 | E9: =-(C9*Assumptions!$B$14+IFERROR(C9/Assumptions!$B$13,0)*Assumptions!$B$15) -> -462000 | F9: =-C9*Assumptions!$B$17 -> -132000 | G9: =D9+E9+F9 -> 594000 | H9: =-Costs!$E$19 -> -251670.72 | I9: =G9+H9 -> 342329.28 | J9: =IF(I9>0,I9*Assumptions!$B$23,I9) -> 171164.64 | K9: =IF(I9>0,I9*(1-Assumptions!$B$23),0) -> 171164.64 | L9: =IFERROR(MAX(J9,0)/Assumptions!$B$24,0) -> 3423.2928
A10: =Assumptions!$B$11 -> 500 | B10: =Assumptions!$B$27 -> 0.06 | C10: =A10*Assumptions!$B$36*12 -> 60000000 | D10: =C10*B10 -> 3600000 | E10: =-(C10*Assumptions!$B$14+IFERROR(C10/Assumptions!$B$13,0)*Assumptions!$B$15) -> -2100000 | F10: =-C10*Assumptions!$B$17 -> -600000 | G10: =D10+E10+F10 -> 900000 | H10: =-Costs!$E$19 -> -251670.72 | I10: =G10+H10 -> 648329.28 | J10: =IF(I10>0,I10*Assumptions!$B$23,I10) -> 324164.64 | K10: =IF(I10>0,I10*(1-Assumptions!$B$23),0) -> 324164.64 | L10: =IFERROR(MAX(J10,0)/Assumptions!$B$24,0) -> 6483.2928
A11: =Assumptions!$B$11 -> 500 | B11: =Assumptions!$B$28 -> 0.07 | C11: =A11*Assumptions!$B$36*12 -> 60000000 | D11: =C11*B11 -> 4200000 | E11: =-(C11*Assumptions!$B$14+IFERROR(C11/Assumptions!$B$13,0)*Assumptions!$B$15) -> -2100000 | F11: =-C11*Assumptions!$B$17 -> -600000 | G11: =D11+E11+F11 -> 1500000 | H11: =-Costs!$E$19 -> -251670.72 | I11: =G11+H11 -> 1248329.3 | J11: =IF(I11>0,I11*Assumptions!$B$23,I11) -> 624164.64 | K11: =IF(I11>0,I11*(1-Assumptions!$B$23),0) -> 624164.64 | L11: =IFERROR(MAX(J11,0)/Assumptions!$B$24,0) -> 12483.293
A12: =Assumptions!$B$11 -> 500 | B12: =Assumptions!$B$29 -> 0.08 | C12: =A12*Assumptions!$B$36*12 -> 60000000 | D12: =C12*B12 -> 4800000 | E12: =-(C12*Assumptions!$B$14+IFERROR(C12/Assumptions!$B$13,0)*Assumptions!$B$15) -> -2100000 | F12: =-C12*Assumptions!$B$17 -> -600000 | G12: =D12+E12+F12 -> 2100000 | H12: =-Costs!$E$19 -> -251670.72 | I12: =G12+H12 -> 1848329.3 | J12: =IF(I12>0,I12*Assumptions!$B$23,I12) -> 924164.64 | K12: =IF(I12>0,I12*(1-Assumptions!$B$23),0) -> 924164.64 | L12: =IFERROR(MAX(J12,0)/Assumptions!$B$24,0) -> 18483.293
A13: =Assumptions!$B$11 -> 500 | B13: =Assumptions!$B$30 -> 0.09 | C13: =A13*Assumptions!$B$36*12 -> 60000000 | D13: =C13*B13 -> 5400000 | E13: =-(C13*Assumptions!$B$14+IFERROR(C13/Assumptions!$B$13,0)*Assumptions!$B$15) -> -2100000 | F13: =-C13*Assumptions!$B$17 -> -600000 | G13: =D13+E13+F13 -> 2700000 | H13: =-Costs!$E$19 -> -251670.72 | I13: =G13+H13 -> 2448329.3 | J13: =IF(I13>0,I13*Assumptions!$B$23,I13) -> 1224164.6 | K13: =IF(I13>0,I13*(1-Assumptions!$B$23),0) -> 1224164.6 | L13: =IFERROR(MAX(J13,0)/Assumptions!$B$24,0) -> 24483.293
A14: =Assumptions!$B$12 -> 2000 | B14: =Assumptions!$B$27 -> 0.06 | C14: =A14*Assumptions!$B$36*12 -> 240000000 | D14: =C14*B14 -> 14400000 | E14: =-(C14*Assumptions!$B$14+IFERROR(C14/Assumptions!$B$13,0)*Assumptions!$B$15) -> -8400000 | F14: =-C14*Assumptions!$B$17 -> -2400000 | G14: =D14+E14+F14 -> 3600000 | H14: =-Costs!$E$19 -> -251670.72 | I14: =G14+H14 -> 3348329.3 | J14: =IF(I14>0,I14*Assumptions!$B$23,I14) -> 1674164.6 | K14: =IF(I14>0,I14*(1-Assumptions!$B$23),0) -> 1674164.6 | L14: =IFERROR(MAX(J14,0)/Assumptions!$B$24,0) -> 33483.293
A15: =Assumptions!$B$12 -> 2000 | B15: =Assumptions!$B$28 -> 0.07 | C15: =A15*Assumptions!$B$36*12 -> 240000000 | D15: =C15*B15 -> 16800000 | E15: =-(C15*Assumptions!$B$14+IFERROR(C15/Assumptions!$B$13,0)*Assumptions!$B$15) -> -8400000 | F15: =-C15*Assumptions!$B$17 -> -2400000 | G15: =D15+E15+F15 -> 6000000 | H15: =-Costs!$E$19 -> -251670.72 | I15: =G15+H15 -> 5748329.3 | J15: =IF(I15>0,I15*Assumptions!$B$23,I15) -> 2874164.6 | K15: =IF(I15>0,I15*(1-Assumptions!$B$23),0) -> 2874164.6 | L15: =IFERROR(MAX(J15,0)/Assumptions!$B$24,0) -> 57483.293
A16: =Assumptions!$B$12 -> 2000 | B16: =Assumptions!$B$29 -> 0.08 | C16: =A16*Assumptions!$B$36*12 -> 240000000 | D16: =C16*B16 -> 19200000 | E16: =-(C16*Assumptions!$B$14+IFERROR(C16/Assumptions!$B$13,0)*Assumptions!$B$15) -> -8400000 | F16: =-C16*Assumptions!$B$17 -> -2400000 | G16: =D16+E16+F16 -> 8400000 | H16: =-Costs!$E$19 -> -251670.72 | I16: =G16+H16 -> 8148329.3 | J16: =IF(I16>0,I16*Assumptions!$B$23,I16) -> 4074164.6 | K16: =IF(I16>0,I16*(1-Assumptions!$B$23),0) -> 4074164.6 | L16: =IFERROR(MAX(J16,0)/Assumptions!$B$24,0) -> 81483.293
A17: =Assumptions!$B$12 -> 2000 | B17: =Assumptions!$B$30 -> 0.09 | C17: =A17*Assumptions!$B$36*12 -> 240000000 | D17: =C17*B17 -> 21600000 | E17: =-(C17*Assumptions!$B$14+IFERROR(C17/Assumptions!$B$13,0)*Assumptions!$B$15) -> -8400000 | F17: =-C17*Assumptions!$B$17 -> -2400000 | G17: =D17+E17+F17 -> 10800000 | H17: =-Costs!$E$19 -> -251670.72 | I17: =G17+H17 -> 10548329 | J17: =IF(I17>0,I17*Assumptions!$B$23,I17) -> 5274164.6 | K17: =IF(I17>0,I17*(1-Assumptions!$B$23),0) -> 5274164.6 | L17: =IFERROR(MAX(J17,0)/Assumptions!$B$24,0) -> 105483.29
A20: 2. STRESSED BY LOSS RATE (mid band, 10,000 sellers)
A21: Fee | B21: =Assumptions!$B$16 -> 0.005 | C21: =Assumptions!$B$17 -> 0.01 | D21: =Assumptions!$B$18 -> 0.02
A22: =Assumptions!$B$27 -> 0.06 | B22: =(Assumptions!$B$11*Assumptions!$B$36*12)*($A22-Assumptions!$B$14-(Assumptions!$B$15/Assumptions!$B$13)-Assumptions!$B$16)-Costs!$E$19 -> 948329.28 | C22: =(Assumptions!$B$11*Assumptions!$B$36*12)*($A22-Assumptions!$B$14-(Assumptions!$B$15/Assumptions!$B$13)-Assumptions!$B$17)-Costs!$E$19 -> 648329.28 | D22: =(Assumptions!$B$11*Assumptions!$B$36*12)*($A22-Assumptions!$B$14-(Assumptions!$B$15/Assumptions!$B$13)-Assumptions!$B$18)-Costs!$E$19 -> 48329.28
A23: =Assumptions!$B$28 -> 0.07 | B23: =(Assumptions!$B$11*Assumptions!$B$36*12)*($A23-Assumptions!$B$14-(Assumptions!$B$15/Assumptions!$B$13)-Assumptions!$B$16)-Costs!$E$19 -> 1548329.3 | C23: =(Assumptions!$B$11*Assumptions!$B$36*12)*($A23-Assumptions!$B$14-(Assumptions!$B$15/Assumptions!$B$13)-Assumptions!$B$17)-Costs!$E$19 -> 1248329.3 | D23: =(Assumptions!$B$11*Assumptions!$B$36*12)*($A23-Assumptions!$B$14-(Assumptions!$B$15/Assumptions!$B$13)-Assumptions!$B$18)-Costs!$E$19 -> 648329.28
A24: =Assumptions!$B$29 -> 0.08 | B24: =(Assumptions!$B$11*Assumptions!$B$36*12)*($A24-Assumptions!$B$14-(Assumptions!$B$15/Assumptions!$B$13)-Assumptions!$B$16)-Costs!$E$19 -> 2148329.3 | C24: =(Assumptions!$B$11*Assumptions!$B$36*12)*($A24-Assumptions!$B$14-(Assumptions!$B$15/Assumptions!$B$13)-Assumptions!$B$17)-Costs!$E$19 -> 1848329.3 | D24: =(Assumptions!$B$11*Assumptions!$B$36*12)*($A24-Assumptions!$B$14-(Assumptions!$B$15/Assumptions!$B$13)-Assumptions!$B$18)-Costs!$E$19 -> 1248329.3
A25: =Assumptions!$B$30 -> 0.09 | B25: =(Assumptions!$B$11*Assumptions!$B$36*12)*($A25-Assumptions!$B$14-(Assumptions!$B$15/Assumptions!$B$13)-Assumptions!$B$16)-Costs!$E$19 -> 2748329.3 | C25: =(Assumptions!$B$11*Assumptions!$B$36*12)*($A25-Assumptions!$B$14-(Assumptions!$B$15/Assumptions!$B$13)-Assumptions!$B$17)-Costs!$E$19 -> 2448329.3 | D25: =(Assumptions!$B$11*Assumptions!$B$36*12)*($A25-Assumptions!$B$14-(Assumptions!$B$15/Assumptions!$B$13)-Assumptions!$B$18)-Costs!$E$19 -> 1848329.3
A27: Every cell is positive, but read the corner: 6% at a 2% loss rate clears only ~$48,000 on $60M of GMV - a 0.08% margin, indistinguishable from zero. 6% stays disqualified even at critical mass. The finding is the 8% row: it stays comfortably profitable across the whole loss band. That is what critical mass buys - being wrong about the loss rate stops being fatal.
A29: 3. WHAT 10,000 SELLERS MEANS OPERATIONALLY (mid band)
A30: Metric | B30: Value | C30: Note
A31: Platform annual GMV | B31: =Assumptions!$B$11*Assumptions!$B$36*12 -> 60000000 | C31: Roughly 0.6% of Etsy's annual GMS
A32: Orders per year | B32: =IFERROR(B31/Assumptions!$B$13,0) -> 1200000 | C32: At the modelled AOV
A33: Orders per day | B33: =IFERROR(B32/365,0) -> 3287.6712 | C33: Sets the real support load
A34: Sellers per support head | B34: =IFERROR(Assumptions!$B$36/Costs!$E$17,0) -> 3333.3333 | C34: vs Etsy ~4,000 per employee at maturity (MEDIUM confidence)
A35: Annual chargeback loss | B35: =B31*Assumptions!$B$17 -> 600000 | C35: Compare to the salary bill below
A36: Annual salary bill | B36: =Costs!$E$18 -> 240000 | C36: 3 FTE at the modelled salary
A37: Loss as multiple of payroll | B37: =IFERROR(B35/B36,0) -> 2.5 | C37: THE ROW TO SIT WITH - fraud is a bigger line item than your team
A40: 4. THE FLYWHEEL - AND ITS TWO CAVEATS
A41: At 10,000 mid-band sellers and 8%, retained earnings fund more new sellers per year than the existing base. The business becomes self-funding for growth.
A42: - CAVEAT 1: the CAC figure is an illustrative placeholder, not researched. It is the single number that makes the flywheel look this good. Get a real one.
A43: - CAVEAT 2: the flywheel describes the state AFTER critical mass. It does not help you REACH 10,000 sellers - that must be funded from outside the model,
A44: - through the hiring valley on the Sensitivity tab, at 6.5x the acquisition cost if sellers turn out to be low-band rather than mid-band.

Sheet Costs (Render)
A1: Operating Cost Stack — Render
A2: Parallel to the original Costs tab. Render replaces BOTH Supabase (database) and Cloudflare Workers (compute), because Render hosts the product as well as the database.
A3: The original Costs tab is unchanged and still feeds the Model, Sensitivity, Profit Targets and 10K Scenario tabs. Only the Blended Model 8% tab reads from THIS tab.
A4: All Render, Cloudflare and R2 list prices below were read from the vendors' own pricing pages in August 2026 — see the PRICE CONSTANTS block. Instance SIZING is an engineering estimate, not a benchmark.
A6: SOFTWARE, BY SELLER COUNT (monthly USD) | B6: 10 | C6: 100 | D6: 1,000 | E6: 10,000 | F6: 20,000 | G6: 40,000 | H6: Confidence / source
A7: Render — workspace plan | B7: 25 | C7: 25 | D7: 25 | E7: 499 | F7: 499 | G7: 499 | H7: HIGH. render.com/pricing: Pro $25/mo, Scale $499/mo. FLAT FEE, not per seat.
A8: Render — web services | B8: =B25*B26 -> 25 | C8: =C25*C26 -> 25 | D8: =D25*D26 -> 170 | E8: =E25*E26 -> 450 | F8: =F25*F26 -> 900 | G8: =G25*G26 -> 1350 | H8: HIGH on unit price, ESTIMATE on sizing. = instance price x count, from the sizing block below.
A9: Render — Postgres (incl. storage) | B9: =B28+B30 -> 19 | C9: =C28+C30 -> 41.2 | D9: =D28+D30 -> 107.2 | E9: =E28+E30 -> 394.7 | F9: =F28+F30 -> 839.7 | G9: =G28+G30 -> 1679.7 | H9: HIGH on unit price, ESTIMATE on sizing and database size.
A10: Render — bandwidth overage | B10: =MAX(0,B31-B32)*$B$39 -> 0 | C10: =MAX(0,C31-C32)*$B$39 -> 0 | D10: =MAX(0,D31-D32)*$B$39 -> 11.25 | E10: =MAX(0,E31-E32)*$B$39 -> 0 | F10: =MAX(0,F31-F32)*$B$39 -> 86.4 | G10: =MAX(0,G31-G32)*$B$39 -> 326.4 | H10: HIGH on rate ($0.15/GB), ESTIMATE on volume. Assumes Cloudflare absorbs most image traffic.
A11: Cloudflare R2 — object storage | B11: =B34+B35 -> 0 | C11: =C34+C35 -> 0.6 | D11: =D34+D35 -> 9.35 | E11: =E34+E35 -> 94.85 | F11: =F34+F35 -> 189.85 | G11: =G34+G35 -> 379.85 | H11: NEW LINE. Render has no object storage; Supabase did. Product images have to live somewhere.
A12: Cloudflare — zone (CDN / DNS) | B12: 0 | C12: 0 | D12: 20 | E12: 20 | F12: 20 | G12: 20 | H12: HIGH. Free covers CDN; Pro $20/mo billed annually. Business ($200/mo) may be needed above 20k.
A13: Canva Pro ($15/seat/mo) | B13: 30 | C13: 30 | D13: 60 | E13: 60 | F13: 90 | G13: 120 | H13: HIGH on unit price. Seats 2/2/4/4/6/8 track staff headcount. 20k/40k are extrapolations.
A14: GitHub Team ($4/user/mo) | B14: 0 | C14: 0 | D14: 16 | E14: 16 | F14: 40 | G14: 60 | H14: HIGH on unit price. Free to 2 staff. 20k/40k are extrapolations.
A15: Domain | B15: 1.56 | C15: 1.56 | D15: 1.56 | E15: 1.56 | F15: 1.56 | G15: 1.56 | H15: HIGH. Fixed regardless of scale.
A16: Customer support (Help Scout Free) | B16: 0 | C16: 0 | D16: 0 | E16: 0 | F16: 0 | G16: 0 | H16: HIGH. Your decision that one shared inbox works at every scale. Increasingly doubtful at 40k.
A17: Email (Kit) | B17: 0 | C17: 0 | D17: 0 | E17: 100 | F17: 200 | G17: 400 | H17: HIGH to 10k subscribers, UNVERIFIED above. Placeholder scaling with list size.
A18: Claude Max 5x ($100/seat/mo) | B18: 200 | C18: 200 | D18: 400 | E18: 400 | F18: 600 | G18: 800 | H18: HIGH on unit price. Seats 2/2/4/4/6/8. Team standard seats would cut this ~80%.
A19: SOFTWARE / MONTH | B19: =SUM(B7:B18) -> 300.56 | C19: =SUM(C7:C18) -> 323.36 | D19: =SUM(D7:D18) -> 820.36 | E19: =SUM(E7:E18) -> 2036.11 | F19: =SUM(F7:F18) -> 3466.51 | G19: =SUM(G7:G18) -> 5636.51 | H19: Sum of the twelve lines above.
A20: SOFTWARE / YEAR | B20: =B19*12 -> 3606.72 | C20: =C19*12 -> 3880.32 | D20: =D19*12 -> 9844.32 | E20: =E19*12 -> 24433.32 | F20: =F19*12 -> 41598.12 | G20: =G19*12 -> 67638.12 | H20: This row is what the Blended Model 8% tab reads.
A22: RENDER + R2 SIZING DETAIL — the inputs that produce rows 8 to 11 above
A23: Render workspace plan | B23: Pro | C23: Pro | D23: Pro | E23: Scale | F23: Scale | G23: Scale | H23: Scale from 10k for horizontal autoscaling and the 1 TB bandwidth allowance.
A24: Web instance type | B24: 1c-2g | C24: 1c-2g | D24: 2c-4g | E24: 4c-16g | F24: 8c-32g | G24: 8c-32g | H24: ESTIMATE. No load testing behind these.
A25: Web instance $/mo each | B25: 25 | C25: 25 | D25: 85 | E25: 225 | F25: 450 | G25: 450 | H25: HIGH. render.com/pricing list prices for the instance types above.
A26: Web instance count | B26: 1 | C26: 1 | D26: 2 | E26: 2 | F26: 2 | G26: 3 | H26: Two instances from 1,000 sellers so a deploy or a crash is not downtime.
A27: Postgres plan | B27: 0.5c-1g | C27: 1c-2g | D27: 2c-8g | E27: 4c-32g | F27: 8c-64g | G27: 16c-128g | H27: ESTIMATE. No read replica and no HA standby costed — see notes.
A28: Postgres base $/mo | B28: 19 | C28: 40 | D28: 100 | E28: 350 | F28: 750 | G28: 1500 | H28: HIGH. render.com/pricing list prices for the plans above.
A29: Database size (GB) | B29: 1 | C29: 5 | D29: 25 | E29: 150 | F29: 300 | G29: 600 | H29: ESTIMATE. Listings, orders and metadata only — images are in R2, not Postgres.
A30: Postgres storage over 1 GB, $/mo | B30: =MAX(0,B29-1)*$B$38 -> 0 | C30: =MAX(0,C29-1)*$B$38 -> 1.2 | D30: =MAX(0,D29-1)*$B$38 -> 7.2 | E30: =MAX(0,E29-1)*$B$38 -> 44.7 | F30: =MAX(0,F29-1)*$B$38 -> 89.7 | G30: =MAX(0,G29-1)*$B$38 -> 179.7 | H30: Formula: (size - 1 GB) x rate in B38.
A31: Origin bandwidth after CDN (GB/mo) | B31: 1 | C31: 10 | D31: 100 | E31: 800 | F31: 1600 | G31: 3200 | H31: ESTIMATE, and a soft one. Assumes Cloudflare caches most image traffic before it reaches Render.
A32: Bandwidth included with plan (GB) | B32: 25 | C32: 25 | D32: 25 | E32: 1024 | F32: 1024 | G32: 1024 | H32: HIGH. Pro includes 25 GB/mo, Scale includes 1 TB/mo.
A33: Image / asset storage in R2 (GB) | B33: 5 | C33: 50 | D33: 500 | E33: 5000 | F33: 10000 | G33: 20000 | H33: ESTIMATE. ~0.5 GB of product images per seller at 40,000 sellers.
A34: R2 storage $/mo | B34: =MAX(0,B33-$B$41)*$B$40 -> 0 | C34: =MAX(0,C33-$B$41)*$B$40 -> 0.6 | D34: =MAX(0,D33-$B$41)*$B$40 -> 7.35 | E34: =MAX(0,E33-$B$41)*$B$40 -> 74.85 | F34: =MAX(0,F33-$B$41)*$B$40 -> 149.85 | G34: =MAX(0,G33-$B$41)*$B$40 -> 299.85 | H34: Formula: (storage - 10 GB free) x rate in B40.
A35: R2 operations $/mo | B35: 0 | C35: 0 | D35: 2 | E35: 20 | F35: 40 | G35: 80 | H35: ESTIMATE. Class A $4.50/M and Class B $0.36/M requests, first 1M/10M free.
A37: PRICE CONSTANTS — read from vendor pricing pages, August 2026
A38: Render Postgres storage, $/GB/mo beyond 1 GB | B38: 0.3 | H38: HIGH. render.com/pricing.
A39: Render bandwidth overage, $/GB | B39: 0.15 | H39: HIGH. render.com/pricing, all plans.
A40: Cloudflare R2 storage, $/GB/mo | B40: 0.015 | H40: HIGH. developers.cloudflare.com/r2/pricing. Egress is free.
A41: Cloudflare R2 free storage allowance (GB) | B41: 10 | H41: HIGH. 10 GB-month free, plus 1M Class A and 10M Class B ops.
A43: WHAT CHANGED vs THE ORIGINAL COSTS TAB
A44: Annual software cost | B44: 10 | C44: 100 | D44: 1,000 | E44: 10,000 | F44: 20,000 | G44: 40,000 | H44: Note
A45: Original stack (Supabase + CF Workers) | B45: =Costs!B$16 -> 3138.72 | C45: =Costs!C$16 -> 3138.72 | D45: =Costs!D$16 -> 6870.72 | E45: =Costs!E$16 -> 11670.72 | F45: no data | G45: no data | H45: The original Costs tab stops at 10,000 sellers.
A46: This tab (Render + R2) | B46: =B20 -> 3606.72 | C46: =C20 -> 3880.32 | D46: =D20 -> 9844.32 | E46: =E20 -> 24433.32 | F46: =F20 -> 41598.12 | G46: =G20 -> 67638.12 | H46: From row 20 above.
A47: Difference | B47: =B46-B45 -> 468 | C47: =C46-C45 -> 741.6 | D47: =D46-D45 -> 2973.6 | E47: =E46-E45 -> 12762.6 | F47: n/a | G47: n/a | H47: Render costs materially more. It is also doing materially more.
A48: Multiple | B48: =IFERROR(B46/B45,0) -> 1.1491054 | C48: =IFERROR(C46/C45,0) -> 1.2362747 | D48: =IFERROR(D46/D45,0) -> 1.4327931 | E48: =IFERROR(E46/E45,0) -> 2.0935572 | F48: n/a | G48: n/a
A50: This is not a like-for-like swap, and the difference is not all price.
A51: - Supabase at $225/mo and Cloudflare Workers at $150/mo were covering database plus edge compute. Nothing in the original stack was a real application server.
A52: - Render is a full application host with a managed Postgres behind it. The jump in cost is partly Render being more expensive and partly the original stack being under-provisioned for a marketplace.
A53: - Object storage is a NEW line, not a price rise. Supabase bundled storage; Render has none. Product images for 40,000 sellers have to live somewhere, and R2 is the cheap answer because its egress is free.
A55: NOT COSTED HERE — each one is a real bill you will eventually receive:
A56: - Postgres high-availability standby, and read replicas for search and browse traffic. Both roughly double the database line.
A57: - Backups beyond what the plan includes, and any point-in-time recovery retention.
A58: - Preview / staging environments, which on Render are billed as additional services.
A59: - Image transformation and resizing (Cloudflare Images or similar) — assumed free here, which it is not.
A60: - Search infrastructure. A 40,000-seller marketplace does not run browse and search off primary Postgres for long.
A62: CONFIDENCE: every LIST PRICE on this tab is HIGH and sourced from the vendor. Every SIZING NUMBER — instance types, counts, database size, bandwidth, storage — is my estimate with no load testing behind it. The list prices will be right; the sizing could be out by a factor of two in either direction.

Sheet Blended Model 8%
A1: Blended Seller Mix — 8% Flat Rate, Three-Year Ramp to 40,000 Sellers
A2: Parallel to the Model tab. The original six tabs are unchanged. Green cells are pulled from other sheets; blue-on-yellow are inputs you can edit.
A3: CHANGES vs the old Model tab: (1) sellers are a MIX of GMV bands; (2) fee fixed at 8%; (3) fraud separated from refunds, with a per-dispute fee; (4) payroll burden at 20%; (5) half-year periods; (6) engineering and trust & safety charged from 10,000 sellers up; (7) software now reads the Costs (Render) tab, not the original Costs tab.
A4: SOFTWARE IS NOW RENDER, NOT SUPABASE. Render replaces both Supabase and Cloudflare Workers, and adds R2 object storage. Costs are line-itemed at all six scale points, so the old 1.7x / 2.8x software multipliers are gone. STILL BEFORE FOUNDER COMPENSATION AND BEFORE CUSTOMER ACQUISITION — both in the MEMO section.
A6: INPUTS | B6: Value | C6: Confidence | D6: Note
A7: Flat platform fee | B7: 0.08 | C7: YOUR DIRECTION | D7: Fixed at 8% per your direction.
A8: Payment processing — % of GMV | B8: =Assumptions!$B$14 -> 0.029 | C8: UNVERIFIED | D8: Stripe US card standard, from Assumptions.
A9: Payment processing — $ per order | B9: =Assumptions!$B$15 -> 0.3 | C9: UNVERIFIED | D9: From Assumptions.
A10: Average order value (AOV) | B10: =Assumptions!$B$13 -> 50 | C10: UNVERIFIED | D10: Drives the fixed processing fee AND the fraud dispute count.
A11: Refund / dispute loss — % of GMV | B11: 0.01 | C11: UNVERIFIED | D11: NON-FRAUD losses: returns, not-as-described, goodwill.
A12: Fraud chargeback rate — % of GMV | B12: 0.004 | C12: UNVERIFIED | D12: Card-not-present fraud. Placeholder. Visa flags a merchant above 0.9%.
A13: Dispute fee per fraud chargeback | B13: 15 | C13: UNVERIFIED | D13: Flat fee per dispute on top of the lost goods. Bites hardest at low AOV.
A14: Support salary per FTE / year | B14: =Assumptions!$B$19 -> 80000 | C14: YOUR DIRECTION | D14: Base pay, from Assumptions.
A15: Payroll burden on all salaries | B15: 0.2 | C15: ESTIMATE | D15: ~20% US W-2 loading. The old model charged 0.
A16: Sellers triggering 1st support FTE | B16: =Assumptions!$B$20 -> 200 | C16: YOUR DIRECTION | D16: From Assumptions. Creates the hiring valley.
A17: Sellers triggering 2nd support FTE | B17: =Assumptions!$B$21 -> 2000 | C17: YOUR DIRECTION
A18: Sellers triggering 3rd support FTE | B18: =Assumptions!$B$22 -> 10000 | C18: YOUR DIRECTION | D18: Also where support switches to a fixed seller-per-head ratio.
A19: Customer acquisition cost per seller | B19: =Assumptions!$B$24 -> 50 | C19: UNVERIFIED | D19: Placeholder from Assumptions. Used only in the MEMO section.
A20: ALL-IN NET TAKE RATE (derived) | B20: =$B$7-$B$8-($B$9/$B$10)-$B$11-$B$12-($B$12*$B$13/$B$10) -> 0.0298 | C20: FORMULA | D20: What the platform keeps per $1 of GMV. Constant at every scale — volume never improves it.
A22: NEW INPUTS FOR SCALE | B22: Value | C22: Confidence | D22: Note
A23: Engineering salary per FTE / year | B23: 150000 | C23: ESTIMATE | D23: NOT RESEARCHED. US senior product engineer, base.
A24: Trust & Safety salary per FTE / year | B24: 65000 | C24: ESTIMATE | D24: NOT RESEARCHED. Fraud / content reviewer, base.
A25: Sellers per support head above 10,000 | B25: 3400 | C25: YOUR DIRECTION | D25: Holds the ~3,333/head ratio you are already at 10,000. Assumes support gets no more efficient.
A27: GMV BANDS | B27: GMV/seller/mo | C27: Confidence | D27: Note
A28: Low band | B28: =Assumptions!$B$10 -> 110 | C28: YOUR DIRECTION | D28: The $110/mo seller.
A29: Mid band | B29: =Assumptions!$B$11 -> 500 | C29: YOUR DIRECTION | D29: Modest but real side-business seller.
A30: High band | B30: =Assumptions!$B$12 -> 2000 | C30: YOUR DIRECTION | D30: Seller running this as primary income.
A32: SELLER MIX VARIATIONS
A33: Share of non-$110 sellers that sit in the Mid band | B33: 0.8 | C33: YOUR DIRECTION | D33: The rest go to the High band. 80/20 gives a thin power-law tail, which is how marketplace GMV distributes.
A34: Variation | B34: % at $110 (Low) | C34: % at Mid | D34: % at High | E34: Blended GMV /seller/mo | F34: Blended GMV /seller/yr | G34: Blended vs $110-only
A35: A — 50% of sellers at $110/mo | B35: 0.5 | C35: =(1-B35)*$B$33 -> 0.4 | D35: =(1-B35)*(1-$B$33) -> 0.1 | E35: =B35*$B$28+C35*$B$29+D35*$B$30 -> 455 | F35: =E35*12 -> 5460 | G35: =IFERROR(E35/$B$28-1,0) -> 3.1363636
A36: B — 70% of sellers at $110/mo | B36: 0.7 | C36: =(1-B36)*$B$33 -> 0.24 | D36: =(1-B36)*(1-$B$33) -> 0.06 | E36: =B36*$B$28+C36*$B$29+D36*$B$30 -> 317 | F36: =E36*12 -> 3804 | G36: =IFERROR(E36/$B$28-1,0) -> 1.8818182
A37: C — 90% of sellers at $110/mo | B37: 0.9 | C37: =(1-B37)*$B$33 -> 0.08 | D37: =(1-B37)*(1-$B$33) -> 0.02 | E37: =B37*$B$28+C37*$B$29+D37*$B$30 -> 179 | F37: =E37*12 -> 2148 | G37: =IFERROR(E37/$B$28-1,0) -> 0.62727273
A40: HEADCOUNT AND SOFTWARE PLAN BY SCALE | B40: Sellers | C40: Support FTE | D40: Engineering FTE | E40: Trust & Safety FTE | F40: Annual software (Render stack) | G40: Sellers per support head | H40: Basis
A41: Scale point 1 | B41: 10 | C41: =IF(B41<=$B$18,IF(B41>=$B$18,3,IF(B41>=$B$17,2,IF(B41>=$B$16,1,0))),ROUNDUP(B41/$B$25,0)) -> 0 | D41: 0 | E41: 0 | F41: ='Costs (Render)'!$B$20 -> 3606.72 | G41: =IFERROR(B41/C41,0) -> 0 | H41: Founders do everything. Software only.
A42: Scale point 2 | B42: 100 | C42: =IF(B42<=$B$18,IF(B42>=$B$18,3,IF(B42>=$B$17,2,IF(B42>=$B$16,1,0))),ROUNDUP(B42/$B$25,0)) -> 0 | D42: 0 | E42: 0 | F42: ='Costs (Render)'!$C$20 -> 3880.32 | G42: =IFERROR(B42/C42,0) -> 0 | H42: Still below the first support hire at 200 sellers.
A43: Scale point 3 | B43: 1000 | C43: =IF(B43<=$B$18,IF(B43>=$B$18,3,IF(B43>=$B$17,2,IF(B43>=$B$16,1,0))),ROUNDUP(B43/$B$25,0)) -> 1 | D43: 0 | E43: 0 | F43: ='Costs (Render)'!$D$20 -> 9844.32 | G43: =IFERROR(B43/C43,0) -> 1000 | H43: First support hire has landed. Engineering is still the founders.
A44: Scale point 4 | B44: 10000 | C44: =IF(B44<=$B$18,IF(B44>=$B$18,3,IF(B44>=$B$17,2,IF(B44>=$B$16,1,0))),ROUNDUP(B44/$B$25,0)) -> 3 | D44: 2 | E44: 1 | F44: ='Costs (Render)'!$E$20 -> 24433.32 | G44: =IFERROR(B44/C44,0) -> 3333.3333 | H44: Founder-built stops working here. 2 engineers, 1 fraud reviewer. Render moves to the Scale plan.
A45: Scale point 5 | B45: 20000 | C45: =IF(B45<=$B$18,IF(B45>=$B$18,3,IF(B45>=$B$17,2,IF(B45>=$B$16,1,0))),ROUNDUP(B45/$B$25,0)) -> 6 | D45: 3 | E45: 2 | F45: ='Costs (Render)'!$F$20 -> 41598.12 | G45: =IFERROR(B45/C45,0) -> 3333.3333 | H45: Support doubles on a held ratio. T&S tracks fraud volume.
A46: Scale point 6 | B46: 40000 | C46: =IF(B46<=$B$18,IF(B46>=$B$18,3,IF(B46>=$B$17,2,IF(B46>=$B$16,1,0))),ROUNDUP(B46/$B$25,0)) -> 12 | D46: 5 | E46: 4 | F46: ='Costs (Render)'!$G$20 -> 67638.12 | G46: =IFERROR(B46/C46,0) -> 3333.3333 | H46: ~4,400 fraud cases per reviewer per year at the 0.40% fraud rate.
A48: Support FTE is a formula: hire thresholds from Assumptions up to 10,000 sellers, then a fixed seller-per-head ratio above that. Engineering and T&S headcount are your inputs, with no research behind them. Software is now line-itemed at all six scale points on the Costs (Render) tab — no multipliers.
A50: VARIATION A — 50% of sellers at $110/mo (blended GMV/seller/mo in E35)
A51: Period | B51: Sellers | C51: Blended GMV /seller/mo | D51: GMV (half-year) | E51: Fee revenue @ 8% | F51: Payment processing | G51: Refunds / disputes | H51: Fraud chargebacks | I51: Net revenue | J51: Software (Render) | K51: Support FTE | L51: Support labour | M51: Eng FTE | N51: Engineering labour | O51: T&S FTE | P51: Trust & Safety labour | Q51: Total operating cost | R51: Profit (half-year) | S51: Cumulative profit | T51: Net take rate | U51: Profit % of GMV | V51: MEMO: profit on OLD cost basis
A52: Year 1 — H1 | B52: =$B$41 -> 10 | C52: =$E$35 -> 455 | D52: =B52*C52*6 -> 27300 | E52: =D52*$B$7 -> 2184 | F52: =-(D52*$B$8+IFERROR(D52/$B$10,0)*$B$9) -> -955.5 | G52: =-D52*$B$11 -> -273 | H52: =-(D52*$B$12+IFERROR(D52*$B$12/$B$10,0)*$B$13) -> -141.96 | I52: =E52+F52+G52+H52 -> 813.54 | J52: =-$F$41/2 -> -1803.36 | K52: =$C$41 -> 0 | L52: =-K52*$B$14*(1+$B$15)/2 -> 0 | M52: =$D$41 -> 0 | N52: =-M52*$B$23*(1+$B$15)/2 -> 0 | O52: =$E$41 -> 0 | P52: =-O52*$B$24*(1+$B$15)/2 -> 0 | Q52: =J52+L52+N52+P52 -> -1803.36 | R52: =I52+Q52 -> -989.82 | S52: =R52 -> -989.82 | T52: =IFERROR(I52/D52,0) -> 0.0298 | U52: =IFERROR(R52/D52,0) -> -0.036257143 | V52: =I52+J52+L52 -> -989.82
A53: Year 1 — H2 | B53: =$B$42 -> 100 | C53: =$E$35 -> 455 | D53: =B53*C53*6 -> 273000 | E53: =D53*$B$7 -> 21840 | F53: =-(D53*$B$8+IFERROR(D53/$B$10,0)*$B$9) -> -9555 | G53: =-D53*$B$11 -> -2730 | H53: =-(D53*$B$12+IFERROR(D53*$B$12/$B$10,0)*$B$13) -> -1419.6 | I53: =E53+F53+G53+H53 -> 8135.4 | J53: =-$F$42/2 -> -1940.16 | K53: =$C$42 -> 0 | L53: =-K53*$B$14*(1+$B$15)/2 -> 0 | M53: =$D$42 -> 0 | N53: =-M53*$B$23*(1+$B$15)/2 -> 0 | O53: =$E$42 -> 0 | P53: =-O53*$B$24*(1+$B$15)/2 -> 0 | Q53: =J53+L53+N53+P53 -> -1940.16 | R53: =I53+Q53 -> 6195.24 | S53: =S52+R53 -> 5205.42 | T53: =IFERROR(I53/D53,0) -> 0.0298 | U53: =IFERROR(R53/D53,0) -> 0.022693187 | V53: =I53+J53+L53 -> 6195.24
A54: Year 2 — H1 | B54: =$B$43 -> 1000 | C54: =$E$35 -> 455 | D54: =B54*C54*6 -> 2730000 | E54: =D54*$B$7 -> 218400 | F54: =-(D54*$B$8+IFERROR(D54/$B$10,0)*$B$9) -> -95550 | G54: =-D54*$B$11 -> -27300 | H54: =-(D54*$B$12+IFERROR(D54*$B$12/$B$10,0)*$B$13) -> -14196 | I54: =E54+F54+G54+H54 -> 81354 | J54: =-$F$43/2 -> -4922.16 | K54: =$C$43 -> 1 | L54: =-K54*$B$14*(1+$B$15)/2 -> -48000 | M54: =$D$43 -> 0 | N54: =-M54*$B$23*(1+$B$15)/2 -> 0 | O54: =$E$43 -> 0 | P54: =-O54*$B$24*(1+$B$15)/2 -> 0 | Q54: =J54+L54+N54+P54 -> -52922.16 | R54: =I54+Q54 -> 28431.84 | S54: =S53+R54 -> 33637.26 | T54: =IFERROR(I54/D54,0) -> 0.0298 | U54: =IFERROR(R54/D54,0) -> 0.010414593 | V54: =I54+J54+L54 -> 28431.84
A55: Year 2 — H2 | B55: =$B$44 -> 10000 | C55: =$E$35 -> 455 | D55: =B55*C55*6 -> 27300000 | E55: =D55*$B$7 -> 2184000 | F55: =-(D55*$B$8+IFERROR(D55/$B$10,0)*$B$9) -> -955500 | G55: =-D55*$B$11 -> -273000 | H55: =-(D55*$B$12+IFERROR(D55*$B$12/$B$10,0)*$B$13) -> -141960 | I55: =E55+F55+G55+H55 -> 813540 | J55: =-$F$44/2 -> -12216.66 | K55: =$C$44 -> 3 | L55: =-K55*$B$14*(1+$B$15)/2 -> -144000 | M55: =$D$44 -> 2 | N55: =-M55*$B$23*(1+$B$15)/2 -> -180000 | O55: =$E$44 -> 1 | P55: =-O55*$B$24*(1+$B$15)/2 -> -39000 | Q55: =J55+L55+N55+P55 -> -375216.66 | R55: =I55+Q55 -> 438323.34 | S55: =S54+R55 -> 471960.6 | T55: =IFERROR(I55/D55,0) -> 0.0298 | U55: =IFERROR(R55/D55,0) -> 0.0160558 | V55: =I55+J55+L55 -> 657323.34
A56: Year 3 — H1 | B56: =$B$45 -> 20000 | C56: =$E$35 -> 455 | D56: =B56*C56*6 -> 54600000 | E56: =D56*$B$7 -> 4368000 | F56: =-(D56*$B$8+IFERROR(D56/$B$10,0)*$B$9) -> -1911000 | G56: =-D56*$B$11 -> -546000 | H56: =-(D56*$B$12+IFERROR(D56*$B$12/$B$10,0)*$B$13) -> -283920 | I56: =E56+F56+G56+H56 -> 1627080 | J56: =-$F$45/2 -> -20799.06 | K56: =$C$45 -> 6 | L56: =-K56*$B$14*(1+$B$15)/2 -> -288000 | M56: =$D$45 -> 3 | N56: =-M56*$B$23*(1+$B$15)/2 -> -270000 | O56: =$E$45 -> 2 | P56: =-O56*$B$24*(1+$B$15)/2 -> -78000 | Q56: =J56+L56+N56+P56 -> -656799.06 | R56: =I56+Q56 -> 970280.94 | S56: =S55+R56 -> 1442241.5 | T56: =IFERROR(I56/D56,0) -> 0.0298 | U56: =IFERROR(R56/D56,0) -> 0.017770713 | V56: =I56+J56+L56 -> 1318280.9
A57: Year 3 — H2 | B57: =$B$46 -> 40000 | C57: =$E$35 -> 455 | D57: =B57*C57*6 -> 109200000 | E57: =D57*$B$7 -> 8736000 | F57: =-(D57*$B$8+IFERROR(D57/$B$10,0)*$B$9) -> -3822000 | G57: =-D57*$B$11 -> -1092000 | H57: =-(D57*$B$12+IFERROR(D57*$B$12/$B$10,0)*$B$13) -> -567840 | I57: =E57+F57+G57+H57 -> 3254160 | J57: =-$F$46/2 -> -33819.06 | K57: =$C$46 -> 12 | L57: =-K57*$B$14*(1+$B$15)/2 -> -576000 | M57: =$D$46 -> 5 | N57: =-M57*$B$23*(1+$B$15)/2 -> -450000 | O57: =$E$46 -> 4 | P57: =-O57*$B$24*(1+$B$15)/2 -> -156000 | Q57: =J57+L57+N57+P57 -> -1215819.1 | R57: =I57+Q57 -> 2038340.9 | S57: =S56+R57 -> 3480582.5 | T57: =IFERROR(I57/D57,0) -> 0.0298 | U57: =IFERROR(R57/D57,0) -> 0.018666126 | V57: =I57+J57+L57 -> 2644340.9
A58: YEAR 1 TOTAL | B58: =B53 -> 100 | C58: =C53 -> 455 | D58: =SUM(D52:D53) -> 300300 | E58: =SUM(E52:E53) -> 24024 | F58: =SUM(F52:F53) -> -10510.5 | G58: =SUM(G52:G53) -> -3003 | H58: =SUM(H52:H53) -> -1561.56 | I58: =SUM(I52:I53) -> 8948.94 | J58: =SUM(J52:J53) -> -3743.52 | K58: =K53 -> 0 | L58: =SUM(L52:L53) -> 0 | M58: =M53 -> 0 | N58: =SUM(N52:N53) -> 0 | O58: =O53 -> 0 | P58: =SUM(P52:P53) -> 0 | Q58: =SUM(Q52:Q53) -> -3743.52 | R58: =SUM(R52:R53) -> 5205.42 | T58: =IFERROR(I58/D58,0) -> 0.0298 | U58: =IFERROR(R58/D58,0) -> 0.017334066 | V58: =SUM(V52:V53) -> 5205.42
A59: YEAR 2 TOTAL | B59: =B55 -> 10000 | C59: =C55 -> 455 | D59: =SUM(D54:D55) -> 30030000 | E59: =SUM(E54:E55) -> 2402400 | F59: =SUM(F54:F55) -> -1051050 | G59: =SUM(G54:G55) -> -300300 | H59: =SUM(H54:H55) -> -156156 | I59: =SUM(I54:I55) -> 894894 | J59: =SUM(J54:J55) -> -17138.82 | K59: =K55 -> 3 | L59: =SUM(L54:L55) -> -192000 | M59: =M55 -> 2 | N59: =SUM(N54:N55) -> -180000 | O59: =O55 -> 1 | P59: =SUM(P54:P55) -> -39000 | Q59: =SUM(Q54:Q55) -> -428138.82 | R59: =SUM(R54:R55) -> 466755.18 | T59: =IFERROR(I59/D59,0) -> 0.0298 | U59: =IFERROR(R59/D59,0) -> 0.015542963 | V59: =SUM(V54:V55) -> 685755.18
A60: YEAR 3 TOTAL | B60: =B57 -> 40000 | C60: =C57 -> 455 | D60: =SUM(D56:D57) -> 163800000 | E60: =SUM(E56:E57) -> 13104000 | F60: =SUM(F56:F57) -> -5733000 | G60: =SUM(G56:G57) -> -1638000 | H60: =SUM(H56:H57) -> -851760 | I60: =SUM(I56:I57) -> 4881240 | J60: =SUM(J56:J57) -> -54618.12 | K60: =K57 -> 12 | L60: =SUM(L56:L57) -> -864000 | M60: =M57 -> 5 | N60: =SUM(N56:N57) -> -720000 | O60: =O57 -> 4 | P60: =SUM(P56:P57) -> -234000 | Q60: =SUM(Q56:Q57) -> -1872618.1 | R60: =SUM(R56:R57) -> 3008621.9 | T60: =IFERROR(I60/D60,0) -> 0.0298 | U60: =IFERROR(R60/D60,0) -> 0.018367655 | V60: =SUM(V56:V57) -> 3962621.9
A61: THREE-YEAR TOTAL | B61: =B57 -> 40000 | C61: =C57 -> 455 | D61: =SUM(D52:D57) -> 194130300 | E61: =SUM(E52:E57) -> 15530424 | F61: =SUM(F52:F57) -> -6794560.5 | G61: =SUM(G52:G57) -> -1941303 | H61: =SUM(H52:H57) -> -1009477.6 | I61: =SUM(I52:I57) -> 5785082.9 | J61: =SUM(J52:J57) -> -75500.46 | K61: =K57 -> 12 | L61: =SUM(L52:L57) -> -1056000 | M61: =M57 -> 5 | N61: =SUM(N52:N57) -> -900000 | O61: =O57 -> 4 | P61: =SUM(P52:P57) -> -273000 | Q61: =SUM(Q52:Q57) -> -2304500.5 | R61: =SUM(R52:R57) -> 3480582.5 | T61: =IFERROR(I61/D61,0) -> 0.0298 | U61: =IFERROR(R61/D61,0) -> 0.017929105 | V61: =SUM(V52:V57) -> 4653582.5
A66: VARIATION B — 70% of sellers at $110/mo (blended GMV/seller/mo in E36)
A67: Period | B67: Sellers | C67: Blended GMV /seller/mo | D67: GMV (half-year) | E67: Fee revenue @ 8% | F67: Payment processing | G67: Refunds / disputes | H67: Fraud chargebacks | I67: Net revenue | J67: Software (Render) | K67: Support FTE | L67: Support labour | M67: Eng FTE | N67: Engineering labour | O67: T&S FTE | P67: Trust & Safety labour | Q67: Total operating cost | R67: Profit (half-year) | S67: Cumulative profit | T67: Net take rate | U67: Profit % of GMV | V67: MEMO: profit on OLD cost basis
A68: Year 1 — H1 | B68: =$B$41 -> 10 | C68: =$E$36 -> 317 | D68: =B68*C68*6 -> 19020 | E68: =D68*$B$7 -> 1521.6 | F68: =-(D68*$B$8+IFERROR(D68/$B$10,0)*$B$9) -> -665.7 | G68: =-D68*$B$11 -> -190.2 | H68: =-(D68*$B$12+IFERROR(D68*$B$12/$B$10,0)*$B$13) -> -98.904 | I68: =E68+F68+G68+H68 -> 566.796 | J68: =-$F$41/2 -> -1803.36 | K68: =$C$41 -> 0 | L68: =-K68*$B$14*(1+$B$15)/2 -> 0 | M68: =$D$41 -> 0 | N68: =-M68*$B$23*(1+$B$15)/2 -> 0 | O68: =$E$41 -> 0 | P68: =-O68*$B$24*(1+$B$15)/2 -> 0 | Q68: =J68+L68+N68+P68 -> -1803.36 | R68: =I68+Q68 -> -1236.564 | S68: =R68 -> -1236.564 | T68: =IFERROR(I68/D68,0) -> 0.0298 | U68: =IFERROR(R68/D68,0) -> -0.06501388 | V68: =I68+J68+L68 -> -1236.564
A69: Year 1 — H2 | B69: =$B$42 -> 100 | C69: =$E$36 -> 317 | D69: =B69*C69*6 -> 190200 | E69: =D69*$B$7 -> 15216 | F69: =-(D69*$B$8+IFERROR(D69/$B$10,0)*$B$9) -> -6657 | G69: =-D69*$B$11 -> -1902 | H69: =-(D69*$B$12+IFERROR(D69*$B$12/$B$10,0)*$B$13) -> -989.04 | I69: =E69+F69+G69+H69 -> 5667.96 | J69: =-$F$42/2 -> -1940.16 | K69: =$C$42 -> 0 | L69: =-K69*$B$14*(1+$B$15)/2 -> 0 | M69: =$D$42 -> 0 | N69: =-M69*$B$23*(1+$B$15)/2 -> 0 | O69: =$E$42 -> 0 | P69: =-O69*$B$24*(1+$B$15)/2 -> 0 | Q69: =J69+L69+N69+P69 -> -1940.16 | R69: =I69+Q69 -> 3727.8 | S69: =S68+R69 -> 2491.236 | T69: =IFERROR(I69/D69,0) -> 0.0298 | U69: =IFERROR(R69/D69,0) -> 0.019599369 | V69: =I69+J69+L69 -> 3727.8
A70: Year 2 — H1 | B70: =$B$43 -> 1000 | C70: =$E$36 -> 317 | D70: =B70*C70*6 -> 1902000 | E70: =D70*$B$7 -> 152160 | F70: =-(D70*$B$8+IFERROR(D70/$B$10,0)*$B$9) -> -66570 | G70: =-D70*$B$11 -> -19020 | H70: =-(D70*$B$12+IFERROR(D70*$B$12/$B$10,0)*$B$13) -> -9890.4 | I70: =E70+F70+G70+H70 -> 56679.6 | J70: =-$F$43/2 -> -4922.16 | K70: =$C$43 -> 1 | L70: =-K70*$B$14*(1+$B$15)/2 -> -48000 | M70: =$D$43 -> 0 | N70: =-M70*$B$23*(1+$B$15)/2 -> 0 | O70: =$E$43 -> 0 | P70: =-O70*$B$24*(1+$B$15)/2 -> 0 | Q70: =J70+L70+N70+P70 -> -52922.16 | R70: =I70+Q70 -> 3757.44 | S70: =S69+R70 -> 6248.676 | T70: =IFERROR(I70/D70,0) -> 0.0298 | U70: =IFERROR(R70/D70,0) -> 0.0019755205 | V70: =I70+J70+L70 -> 3757.44
A71: Year 2 — H2 | B71: =$B$44 -> 10000 | C71: =$E$36 -> 317 | D71: =B71*C71*6 -> 19020000 | E71: =D71*$B$7 -> 1521600 | F71: =-(D71*$B$8+IFERROR(D71/$B$10,0)*$B$9) -> -665700 | G71: =-D71*$B$11 -> -190200 | H71: =-(D71*$B$12+IFERROR(D71*$B$12/$B$10,0)*$B$13) -> -98904 | I71: =E71+F71+G71+H71 -> 566796 | J71: =-$F$44/2 -> -12216.66 | K71: =$C$44 -> 3 | L71: =-K71*$B$14*(1+$B$15)/2 -> -144000 | M71: =$D$44 -> 2 | N71: =-M71*$B$23*(1+$B$15)/2 -> -180000 | O71: =$E$44 -> 1 | P71: =-O71*$B$24*(1+$B$15)/2 -> -39000 | Q71: =J71+L71+N71+P71 -> -375216.66 | R71: =I71+Q71 -> 191579.34 | S71: =S70+R71 -> 197828.02 | T71: =IFERROR(I71/D71,0) -> 0.0298 | U71: =IFERROR(R71/D71,0) -> 0.010072521 | V71: =I71+J71+L71 -> 410579.34
A72: Year 3 — H1 | B72: =$B$45 -> 20000 | C72: =$E$36 -> 317 | D72: =B72*C72*6 -> 38040000 | E72: =D72*$B$7 -> 3043200 | F72: =-(D72*$B$8+IFERROR(D72/$B$10,0)*$B$9) -> -1331400 | G72: =-D72*$B$11 -> -380400 | H72: =-(D72*$B$12+IFERROR(D72*$B$12/$B$10,0)*$B$13) -> -197808 | I72: =E72+F72+G72+H72 -> 1133592 | J72: =-$F$45/2 -> -20799.06 | K72: =$C$45 -> 6 | L72: =-K72*$B$14*(1+$B$15)/2 -> -288000 | M72: =$D$45 -> 3 | N72: =-M72*$B$23*(1+$B$15)/2 -> -270000 | O72: =$E$45 -> 2 | P72: =-O72*$B$24*(1+$B$15)/2 -> -78000 | Q72: =J72+L72+N72+P72 -> -656799.06 | R72: =I72+Q72 -> 476792.94 | S72: =S71+R72 -> 674620.96 | T72: =IFERROR(I72/D72,0) -> 0.0298 | U72: =IFERROR(R72/D72,0) -> 0.012533989 | V72: =I72+J72+L72 -> 824792.94
A73: Year 3 — H2 | B73: =$B$46 -> 40000 | C73: =$E$36 -> 317 | D73: =B73*C73*6 -> 76080000 | E73: =D73*$B$7 -> 6086400 | F73: =-(D73*$B$8+IFERROR(D73/$B$10,0)*$B$9) -> -2662800 | G73: =-D73*$B$11 -> -760800 | H73: =-(D73*$B$12+IFERROR(D73*$B$12/$B$10,0)*$B$13) -> -395616 | I73: =E73+F73+G73+H73 -> 2267184 | J73: =-$F$46/2 -> -33819.06 | K73: =$C$46 -> 12 | L73: =-K73*$B$14*(1+$B$15)/2 -> -576000 | M73: =$D$46 -> 5 | N73: =-M73*$B$23*(1+$B$15)/2 -> -450000 | O73: =$E$46 -> 4 | P73: =-O73*$B$24*(1+$B$15)/2 -> -156000 | Q73: =J73+L73+N73+P73 -> -1215819.1 | R73: =I73+Q73 -> 1051364.9 | S73: =S72+R73 -> 1725985.9 | T73: =IFERROR(I73/D73,0) -> 0.0298 | U73: =IFERROR(R73/D73,0) -> 0.013819203 | V73: =I73+J73+L73 -> 1657364.9
A74: YEAR 1 TOTAL | B74: =B69 -> 100 | C74: =C69 -> 317 | D74: =SUM(D68:D69) -> 209220 | E74: =SUM(E68:E69) -> 16737.6 | F74: =SUM(F68:F69) -> -7322.7 | G74: =SUM(G68:G69) -> -2092.2 | H74: =SUM(H68:H69) -> -1087.944 | I74: =SUM(I68:I69) -> 6234.756 | J74: =SUM(J68:J69) -> -3743.52 | K74: =K69 -> 0 | L74: =SUM(L68:L69) -> 0 | M74: =M69 -> 0 | N74: =SUM(N68:N69) -> 0 | O74: =O69 -> 0 | P74: =SUM(P68:P69) -> 0 | Q74: =SUM(Q68:Q69) -> -3743.52 | R74: =SUM(R68:R69) -> 2491.236 | T74: =IFERROR(I74/D74,0) -> 0.0298 | U74: =IFERROR(R74/D74,0) -> 0.011907256 | V74: =SUM(V68:V69) -> 2491.236
A75: YEAR 2 TOTAL | B75: =B71 -> 10000 | C75: =C71 -> 317 | D75: =SUM(D70:D71) -> 20922000 | E75: =SUM(E70:E71) -> 1673760 | F75: =SUM(F70:F71) -> -732270 | G75: =SUM(G70:G71) -> -209220 | H75: =SUM(H70:H71) -> -108794.4 | I75: =SUM(I70:I71) -> 623475.6 | J75: =SUM(J70:J71) -> -17138.82 | K75: =K71 -> 3 | L75: =SUM(L70:L71) -> -192000 | M75: =M71 -> 2 | N75: =SUM(N70:N71) -> -180000 | O75: =O71 -> 1 | P75: =SUM(P70:P71) -> -39000 | Q75: =SUM(Q70:Q71) -> -428138.82 | R75: =SUM(R70:R71) -> 195336.78 | T75: =IFERROR(I75/D75,0) -> 0.0298 | U75: =IFERROR(R75/D75,0) -> 0.0093364296 | V75: =SUM(V70:V71) -> 414336.78
A76: YEAR 3 TOTAL | B76: =B73 -> 40000 | C76: =C73 -> 317 | D76: =SUM(D72:D73) -> 114120000 | E76: =SUM(E72:E73) -> 9129600 | F76: =SUM(F72:F73) -> -3994200 | G76: =SUM(G72:G73) -> -1141200 | H76: =SUM(H72:H73) -> -593424 | I76: =SUM(I72:I73) -> 3400776 | J76: =SUM(J72:J73) -> -54618.12 | K76: =K73 -> 12 | L76: =SUM(L72:L73) -> -864000 | M76: =M73 -> 5 | N76: =SUM(N72:N73) -> -720000 | O76: =O73 -> 4 | P76: =SUM(P72:P73) -> -234000 | Q76: =SUM(Q72:Q73) -> -1872618.1 | R76: =SUM(R72:R73) -> 1528157.9 | T76: =IFERROR(I76/D76,0) -> 0.0298 | U76: =IFERROR(R76/D76,0) -> 0.013390798 | V76: =SUM(V72:V73) -> 2482157.9
A77: THREE-YEAR TOTAL | B77: =B73 -> 40000 | C77: =C73 -> 317 | D77: =SUM(D68:D73) -> 135251220 | E77: =SUM(E68:E73) -> 10820098 | F77: =SUM(F68:F73) -> -4733792.7 | G77: =SUM(G68:G73) -> -1352512.2 | H77: =SUM(H68:H73) -> -703306.34 | I77: =SUM(I68:I73) -> 4030486.4 | J77: =SUM(J68:J73) -> -75500.46 | K77: =K73 -> 12 | L77: =SUM(L68:L73) -> -1056000 | M77: =M73 -> 5 | N77: =SUM(N68:N73) -> -900000 | O77: =O73 -> 4 | P77: =SUM(P68:P73) -> -273000 | Q77: =SUM(Q68:Q73) -> -2304500.5 | R77: =SUM(R68:R73) -> 1725985.9 | T77: =IFERROR(I77/D77,0) -> 0.0298 | U77: =IFERROR(R77/D77,0) -> 0.012761333 | V77: =SUM(V68:V73) -> 2898985.9
A82: VARIATION C — 90% of sellers at $110/mo (blended GMV/seller/mo in E37)
A83: Period | B83: Sellers | C83: Blended GMV /seller/mo | D83: GMV (half-year) | E83: Fee revenue @ 8% | F83: Payment processing | G83: Refunds / disputes | H83: Fraud chargebacks | I83: Net revenue | J83: Software (Render) | K83: Support FTE | L83: Support labour | M83: Eng FTE | N83: Engineering labour | O83: T&S FTE | P83: Trust & Safety labour | Q83: Total operating cost | R83: Profit (half-year) | S83: Cumulative profit | T83: Net take rate | U83: Profit % of GMV | V83: MEMO: profit on OLD cost basis
A84: Year 1 — H1 | B84: =$B$41 -> 10 | C84: =$E$37 -> 179 | D84: =B84*C84*6 -> 10740 | E84: =D84*$B$7 -> 859.2 | F84: =-(D84*$B$8+IFERROR(D84/$B$10,0)*$B$9) -> -375.9 | G84: =-D84*$B$11 -> -107.4 | H84: =-(D84*$B$12+IFERROR(D84*$B$12/$B$10,0)*$B$13) -> -55.848 | I84: =E84+F84+G84+H84 -> 320.052 | J84: =-$F$41/2 -> -1803.36 | K84: =$C$41 -> 0 | L84: =-K84*$B$14*(1+$B$15)/2 -> 0 | M84: =$D$41 -> 0 | N84: =-M84*$B$23*(1+$B$15)/2 -> 0 | O84: =$E$41 -> 0 | P84: =-O84*$B$24*(1+$B$15)/2 -> 0 | Q84: =J84+L84+N84+P84 -> -1803.36 | R84: =I84+Q84 -> -1483.308 | S84: =R84 -> -1483.308 | T84: =IFERROR(I84/D84,0) -> 0.0298 | U84: =IFERROR(R84/D84,0) -> -0.13811061 | V84: =I84+J84+L84 -> -1483.308
A85: Year 1 — H2 | B85: =$B$42 -> 100 | C85: =$E$37 -> 179 | D85: =B85*C85*6 -> 107400 | E85: =D85*$B$7 -> 8592 | F85: =-(D85*$B$8+IFERROR(D85/$B$10,0)*$B$9) -> -3759 | G85: =-D85*$B$11 -> -1074 | H85: =-(D85*$B$12+IFERROR(D85*$B$12/$B$10,0)*$B$13) -> -558.48 | I85: =E85+F85+G85+H85 -> 3200.52 | J85: =-$F$42/2 -> -1940.16 | K85: =$C$42 -> 0 | L85: =-K85*$B$14*(1+$B$15)/2 -> 0 | M85: =$D$42 -> 0 | N85: =-M85*$B$23*(1+$B$15)/2 -> 0 | O85: =$E$42 -> 0 | P85: =-O85*$B$24*(1+$B$15)/2 -> 0 | Q85: =J85+L85+N85+P85 -> -1940.16 | R85: =I85+Q85 -> 1260.36 | S85: =S84+R85 -> -222.948 | T85: =IFERROR(I85/D85,0) -> 0.0298 | U85: =IFERROR(R85/D85,0) -> 0.011735196 | V85: =I85+J85+L85 -> 1260.36
A86: Year 2 — H1 | B86: =$B$43 -> 1000 | C86: =$E$37 -> 179 | D86: =B86*C86*6 -> 1074000 | E86: =D86*$B$7 -> 85920 | F86: =-(D86*$B$8+IFERROR(D86/$B$10,0)*$B$9) -> -37590 | G86: =-D86*$B$11 -> -10740 | H86: =-(D86*$B$12+IFERROR(D86*$B$12/$B$10,0)*$B$13) -> -5584.8 | I86: =E86+F86+G86+H86 -> 32005.2 | J86: =-$F$43/2 -> -4922.16 | K86: =$C$43 -> 1 | L86: =-K86*$B$14*(1+$B$15)/2 -> -48000 | M86: =$D$43 -> 0 | N86: =-M86*$B$23*(1+$B$15)/2 -> 0 | O86: =$E$43 -> 0 | P86: =-O86*$B$24*(1+$B$15)/2 -> 0 | Q86: =J86+L86+N86+P86 -> -52922.16 | R86: =I86+Q86 -> -20916.96 | S86: =S85+R86 -> -21139.908 | T86: =IFERROR(I86/D86,0) -> 0.0298 | U86: =IFERROR(R86/D86,0) -> -0.019475754 | V86: =I86+J86+L86 -> -20916.96
A87: Year 2 — H2 | B87: =$B$44 -> 10000 | C87: =$E$37 -> 179 | D87: =B87*C87*6 -> 10740000 | E87: =D87*$B$7 -> 859200 | F87: =-(D87*$B$8+IFERROR(D87/$B$10,0)*$B$9) -> -375900 | G87: =-D87*$B$11 -> -107400 | H87: =-(D87*$B$12+IFERROR(D87*$B$12/$B$10,0)*$B$13) -> -55848 | I87: =E87+F87+G87+H87 -> 320052 | J87: =-$F$44/2 -> -12216.66 | K87: =$C$44 -> 3 | L87: =-K87*$B$14*(1+$B$15)/2 -> -144000 | M87: =$D$44 -> 2 | N87: =-M87*$B$23*(1+$B$15)/2 -> -180000 | O87: =$E$44 -> 1 | P87: =-O87*$B$24*(1+$B$15)/2 -> -39000 | Q87: =J87+L87+N87+P87 -> -375216.66 | R87: =I87+Q87 -> -55164.66 | S87: =S86+R87 -> -76304.568 | T87: =IFERROR(I87/D87,0) -> 0.0298 | U87: =IFERROR(R87/D87,0) -> -0.0051363743 | V87: =I87+J87+L87 -> 163835.34
A88: Year 3 — H1 | B88: =$B$45 -> 20000 | C88: =$E$37 -> 179 | D88: =B88*C88*6 -> 21480000 | E88: =D88*$B$7 -> 1718400 | F88: =-(D88*$B$8+IFERROR(D88/$B$10,0)*$B$9) -> -751800 | G88: =-D88*$B$11 -> -214800 | H88: =-(D88*$B$12+IFERROR(D88*$B$12/$B$10,0)*$B$13) -> -111696 | I88: =E88+F88+G88+H88 -> 640104 | J88: =-$F$45/2 -> -20799.06 | K88: =$C$45 -> 6 | L88: =-K88*$B$14*(1+$B$15)/2 -> -288000 | M88: =$D$45 -> 3 | N88: =-M88*$B$23*(1+$B$15)/2 -> -270000 | O88: =$E$45 -> 2 | P88: =-O88*$B$24*(1+$B$15)/2 -> -78000 | Q88: =J88+L88+N88+P88 -> -656799.06 | R88: =I88+Q88 -> -16695.06 | S88: =S87+R88 -> -92999.628 | T88: =IFERROR(I88/D88,0) -> 0.0298 | U88: =IFERROR(R88/D88,0) -> -0.00077723743 | V88: =I88+J88+L88 -> 331304.94
A89: Year 3 — H2 | B89: =$B$46 -> 40000 | C89: =$E$37 -> 179 | D89: =B89*C89*6 -> 42960000 | E89: =D89*$B$7 -> 3436800 | F89: =-(D89*$B$8+IFERROR(D89/$B$10,0)*$B$9) -> -1503600 | G89: =-D89*$B$11 -> -429600 | H89: =-(D89*$B$12+IFERROR(D89*$B$12/$B$10,0)*$B$13) -> -223392 | I89: =E89+F89+G89+H89 -> 1280208 | J89: =-$F$46/2 -> -33819.06 | K89: =$C$46 -> 12 | L89: =-K89*$B$14*(1+$B$15)/2 -> -576000 | M89: =$D$46 -> 5 | N89: =-M89*$B$23*(1+$B$15)/2 -> -450000 | O89: =$E$46 -> 4 | P89: =-O89*$B$24*(1+$B$15)/2 -> -156000 | Q89: =J89+L89+N89+P89 -> -1215819.1 | R89: =I89+Q89 -> 64388.94 | S89: =S88+R89 -> -28610.688 | T89: =IFERROR(I89/D89,0) -> 0.0298 | U89: =IFERROR(R89/D89,0) -> 0.0014988115 | V89: =I89+J89+L89 -> 670388.94
A90: YEAR 1 TOTAL | B90: =B85 -> 100 | C90: =C85 -> 179 | D90: =SUM(D84:D85) -> 118140 | E90: =SUM(E84:E85) -> 9451.2 | F90: =SUM(F84:F85) -> -4134.9 | G90: =SUM(G84:G85) -> -1181.4 | H90: =SUM(H84:H85) -> -614.328 | I90: =SUM(I84:I85) -> 3520.572 | J90: =SUM(J84:J85) -> -3743.52 | K90: =K85 -> 0 | L90: =SUM(L84:L85) -> 0 | M90: =M85 -> 0 | N90: =SUM(N84:N85) -> 0 | O90: =O85 -> 0 | P90: =SUM(P84:P85) -> 0 | Q90: =SUM(Q84:Q85) -> -3743.52 | R90: =SUM(R84:R85) -> -222.948 | T90: =IFERROR(I90/D90,0) -> 0.0298 | U90: =IFERROR(R90/D90,0) -> -0.0018871508 | V90: =SUM(V84:V85) -> -222.948
A91: YEAR 2 TOTAL | B91: =B87 -> 10000 | C91: =C87 -> 179 | D91: =SUM(D86:D87) -> 11814000 | E91: =SUM(E86:E87) -> 945120 | F91: =SUM(F86:F87) -> -413490 | G91: =SUM(G86:G87) -> -118140 | H91: =SUM(H86:H87) -> -61432.8 | I91: =SUM(I86:I87) -> 352057.2 | J91: =SUM(J86:J87) -> -17138.82 | K91: =K87 -> 3 | L91: =SUM(L86:L87) -> -192000 | M91: =M87 -> 2 | N91: =SUM(N86:N87) -> -180000 | O91: =O87 -> 1 | P91: =SUM(P86:P87) -> -39000 | Q91: =SUM(Q86:Q87) -> -428138.82 | R91: =SUM(R86:R87) -> -76081.62 | T91: =IFERROR(I91/D91,0) -> 0.0298 | U91: =IFERROR(R91/D91,0) -> -0.0064399543 | V91: =SUM(V86:V87) -> 142918.38
A92: YEAR 3 TOTAL | B92: =B89 -> 40000 | C92: =C89 -> 179 | D92: =SUM(D88:D89) -> 64440000 | E92: =SUM(E88:E89) -> 5155200 | F92: =SUM(F88:F89) -> -2255400 | G92: =SUM(G88:G89) -> -644400 | H92: =SUM(H88:H89) -> -335088 | I92: =SUM(I88:I89) -> 1920312 | J92: =SUM(J88:J89) -> -54618.12 | K92: =K89 -> 12 | L92: =SUM(L88:L89) -> -864000 | M92: =M89 -> 5 | N92: =SUM(N88:N89) -> -720000 | O92: =O89 -> 4 | P92: =SUM(P88:P89) -> -234000 | Q92: =SUM(Q88:Q89) -> -1872618.1 | R92: =SUM(R88:R89) -> 47693.88 | T92: =IFERROR(I92/D92,0) -> 0.0298 | U92: =IFERROR(R92/D92,0) -> 0.00074012849 | V92: =SUM(V88:V89) -> 1001693.9
A93: THREE-YEAR TOTAL | B93: =B89 -> 40000 | C93: =C89 -> 179 | D93: =SUM(D84:D89) -> 76372140 | E93: =SUM(E84:E89) -> 6109771.2 | F93: =SUM(F84:F89) -> -2673024.9 | G93: =SUM(G84:G89) -> -763721.4 | H93: =SUM(H84:H89) -> -397135.13 | I93: =SUM(I84:I89) -> 2275889.8 | J93: =SUM(J84:J89) -> -75500.46 | K93: =K89 -> 12 | L93: =SUM(L84:L89) -> -1056000 | M93: =M89 -> 5 | N93: =SUM(N84:N89) -> -900000 | O93: =O89 -> 4 | P93: =SUM(P84:P89) -> -273000 | Q93: =SUM(Q84:Q89) -> -2304500.5 | R93: =SUM(R84:R89) -> -28610.688 | T93: =IFERROR(I93/D93,0) -> 0.0298 | U93: =IFERROR(R93/D93,0) -> -0.00037462205 | V93: =SUM(V84:V89) -> 1144389.3
A98: SUMMARY — THE THREE VARIATIONS | B98: Variation A 50% at $110 | C98: Variation B 70% at $110 | D98: Variation C 90% at $110 | E98: Read
A99: Blended GMV per seller / month | B99: =E35 -> 455 | C99: =E36 -> 317 | D99: =E37 -> 179 | E99: The whole model turns on this.
A100: Year 1 profit (10 then 100 sellers) | B100: =R58 -> 5205.42 | C100: =R74 -> 2491.236 | D100: =R90 -> -222.948 | E100: Rounding error either way.
A101: Year 2 profit (1,000 then 10,000) | B101: =R59 -> 466755.18 | C101: =R75 -> 195336.78 | D101: =R91 -> -76081.62 | E101: Carries engineering, T&S and the Render Scale plan at the 10,000 step.
A102: Year 3 profit (20,000 then 40,000) | B102: =R60 -> 3008621.9 | C102: =R76 -> 1528157.9 | D102: =R92 -> 47693.88 | E102: Where the business either works or does not.
A103: THREE-YEAR CUMULATIVE PROFIT | B103: =R61 -> 3480582.5 | C103: =R77 -> 1725985.9 | D103: =R93 -> -28610.688 | E103: Before founder pay and before acquisition. See MEMO.
A104: Annual profit run-rate at 10,000 | B104: =R55*2 -> 876646.68 | C104: =R71*2 -> 383158.68 | D104: =R87*2 -> -110329.32 | E104: Half-year period annualised.
A105: Annual profit run-rate at 20,000 | B105: =R56*2 -> 1940561.9 | C105: =R72*2 -> 953585.88 | D105: =R88*2 -> -33390.12
A106: Annual profit run-rate at 40,000 | B106: =R57*2 -> 4076681.9 | C106: =R73*2 -> 2102729.9 | D106: =R89*2 -> 128777.88 | E106: The end state this tab reaches.
A107: Annual GMV run-rate at 40,000 | B107: =D57*2 -> 218400000 | C107: =D73*2 -> 152160000 | D107: =D89*2 -> 85920000
A108: All-in net take rate | B108: =$B$20 -> 0.0298 | C108: =$B$20 -> 0.0298 | D108: =$B$20 -> 0.0298 | E108: Identical everywhere. Scale changes volume, never the rate.
A109: Annual software cost at 40,000 | B109: =-J57*2 -> 67638.12 | C109: =-J73*2 -> 67638.12 | D109: =-J89*2 -> 67638.12 | E109: The Render stack. Compare to the old stack on the Costs (Render) tab, row 47.
A110: Software as % of operating cost at 40,000 | B110: =IFERROR(J57/Q57,0) -> 0.027815866 | C110: =IFERROR(J73/Q73,0) -> 0.027815866 | D110: =IFERROR(J89/Q89,0) -> 0.027815866 | E110: Still small. Labour dominates at every scale — the vendor swap does not change that.
A111: Profit margin on GMV at 40,000 | B111: =IFERROR(R57/D57,0) -> 0.018666126 | C111: =IFERROR(R73/D73,0) -> 0.013819203 | D111: =IFERROR(R89/D89,0) -> 0.0014988115 | E111: Operating leverage, or its absence.
A112: Fraud + refunds, three-year total | B112: =G61+H61 -> -2950780.6 | C112: =G77+H77 -> -2055818.5 | D112: =G93+H93 -> -1160856.5 | E112: Grows strictly with GMV. Scale never improves it.
A113: Fraud as % of net revenue | B113: =IFERROR(-H57/I57,0) -> 0.17449664 | C113: =IFERROR(-H73/I73,0) -> 0.17449664 | D113: =IFERROR(-H89/I89,0) -> 0.17449664 | E113: Constant at every scale and in every variation.
A116: WHAT SCALE ACTUALLY DOES — ANNUALISED, VARIATION B (70% at $110) AS THE BASE CASE
A117: Annualised = the half-year period doubled. Variation B is the middle case; the pattern is identical in A and C, only the level moves.
A118: Metric | B118: At 1,000 sellers | C118: At 10,000 sellers | D118: At 20,000 sellers | E118: At 40,000 sellers | F118: Read
A119: Annual GMV | B119: =D70*2 -> 3804000 | C119: =D71*2 -> 38040000 | D119: =D72*2 -> 76080000 | E119: =D73*2 -> 152160000 | F119: Grows exactly linearly with sellers.
A120: Annual net revenue | B120: =I70*2 -> 113359.2 | C120: =I71*2 -> 1133592 | D120: =I72*2 -> 2267184 | E120: =I73*2 -> 4534368 | F120: Also linear — the take rate never improves.
A121: Annual software (Render) | B121: =-J70*2 -> 9844.32 | C121: =-J71*2 -> 24433.32 | D121: =-J72*2 -> 41598.12 | E121: =-J73*2 -> 67638.12 | F121: Grows, but it is the smallest cost line at every scale.
A122: Annual operating cost | B122: =-Q70*2 -> 105844.32 | C122: =-Q71*2 -> 750433.32 | D122: =-Q72*2 -> 1313598.1 | E122: =-Q73*2 -> 2431638.1 | F122: Grows in steps, slower than revenue. This is the whole game.
...
